{
"meta":{"test_sets":[],"test_metrics":[],"learn_metrics":[{"best_value":"Min","name":"CrossEntropy"}],"launch_mode":"Train","parameters":"","iteration_count":1000,"learn_sets":["learn"],"name":"experiment"},
"iterations":[
{"learn":[0.6437646347],"iteration":0,"passed_time":0.157377564,"remaining_time":157.2201864},
{"learn":[0.6158046349],"iteration":1,"passed_time":0.1656865258,"remaining_time":82.67757637},
{"learn":[0.5904348485],"iteration":2,"passed_time":0.1701132451,"remaining_time":56.5343018},
{"learn":[0.5634180354],"iteration":3,"passed_time":0.1758140925,"remaining_time":43.77770904},
{"learn":[0.5499051672],"iteration":4,"passed_time":0.1837268565,"remaining_time":36.56164444},
{"learn":[0.5276449682],"iteration":5,"passed_time":0.1921218789,"remaining_time":31.82819128},
{"learn":[0.5135643776],"iteration":6,"passed_time":0.200884796,"remaining_time":28.4969432},
{"learn":[0.505669626],"iteration":7,"passed_time":0.2090018676,"remaining_time":25.91623158},
{"learn":[0.4927469932],"iteration":8,"passed_time":0.2162793116,"remaining_time":23.81475531},
{"learn":[0.4887071246],"iteration":9,"passed_time":0.2243665237,"remaining_time":22.21228585},
{"learn":[0.4841415612],"iteration":10,"passed_time":0.231864034,"remaining_time":20.84668451},
{"learn":[0.4804852003],"iteration":11,"passed_time":0.2395530912,"remaining_time":19.72320451},
{"learn":[0.4745327226],"iteration":12,"passed_time":0.2465432411,"remaining_time":18.71832146},
{"learn":[0.4728821414],"iteration":13,"passed_time":0.2539787452,"remaining_time":17.8873602},
{"learn":[0.4709440518],"iteration":14,"passed_time":0.2618412805,"remaining_time":17.19424409},
{"learn":[0.4682248586],"iteration":15,"passed_time":0.2713849576,"remaining_time":16.69017489},
{"learn":[0.4658365057],"iteration":16,"passed_time":0.2785386509,"remaining_time":16.10608788},
{"learn":[0.4610687343],"iteration":17,"passed_time":0.2852592193,"remaining_time":15.56247518},
{"learn":[0.4549715644],"iteration":18,"passed_time":0.2923906999,"remaining_time":15.09659351},
{"learn":[0.4516796856],"iteration":19,"passed_time":0.2989518439,"remaining_time":14.64864035},
{"learn":[0.4491763547],"iteration":20,"passed_time":0.3064573635,"remaining_time":14.28675042},
{"learn":[0.4439297818],"iteration":21,"passed_time":0.3142048377,"remaining_time":13.96783324},
{"learn":[0.4409150766],"iteration":22,"passed_time":0.3227976654,"remaining_time":13.71188344},
{"learn":[0.4371234302],"iteration":23,"passed_time":0.3326724494,"remaining_time":13.52867961},
{"learn":[0.4339392118],"iteration":24,"passed_time":0.3396851716,"remaining_time":13.24772169},
{"learn":[0.4317918919],"iteration":25,"passed_time":0.3462579128,"remaining_time":12.97135412},
{"learn":[0.4274050901],"iteration":26,"passed_time":0.3554552484,"remaining_time":12.80955395},
{"learn":[0.4249858519],"iteration":27,"passed_time":0.3641473883,"remaining_time":12.64111648},
{"learn":[0.422494046],"iteration":28,"passed_time":0.3713242064,"remaining_time":12.43295877},
{"learn":[0.4197594013],"iteration":29,"passed_time":0.3802823214,"remaining_time":12.29579506},
{"learn":[0.4166232825],"iteration":30,"passed_time":0.3884478263,"remaining_time":12.14212722},
{"learn":[0.4147222399],"iteration":31,"passed_time":0.3990878649,"remaining_time":12.07240791},
{"learn":[0.4132837543],"iteration":32,"passed_time":0.4090680747,"remaining_time":11.98693419},
{"learn":[0.4120008983],"iteration":33,"passed_time":0.4168663703,"remaining_time":11.84390923},
{"learn":[0.4107713387],"iteration":34,"passed_time":0.42424883,"remaining_time":11.69714631},
{"learn":[0.4091398862],"iteration":35,"passed_time":0.4316593742,"remaining_time":11.5588788},
{"learn":[0.4079789417],"iteration":36,"passed_time":0.4392998889,"remaining_time":11.43367008},
{"learn":[0.4056294315],"iteration":37,"passed_time":0.4476952349,"remaining_time":11.33375832},
{"learn":[0.4040192166],"iteration":38,"passed_time":0.4555677737,"remaining_time":11.22565719},
{"learn":[0.4030903198],"iteration":39,"passed_time":0.463950939,"remaining_time":11.13482254},
{"learn":[0.4023216193],"iteration":40,"passed_time":0.471102176,"remaining_time":11.0191948},
{"learn":[0.4018999903],"iteration":41,"passed_time":0.4783182856,"remaining_time":10.91021232},
{"learn":[0.4008208341],"iteration":42,"passed_time":0.4847314732,"remaining_time":10.78809349},
{"learn":[0.3998869926],"iteration":43,"passed_time":0.4923069255,"remaining_time":10.69648683},
{"learn":[0.3993266768],"iteration":44,"passed_time":0.5006701556,"remaining_time":10.6253333},
{"learn":[0.3990924091],"iteration":45,"passed_time":0.5086187928,"remaining_time":10.54831149},
{"learn":[0.3973919741],"iteration":46,"passed_time":0.5169410748,"remaining_time":10.4818052},
{"learn":[0.3967119139],"iteration":47,"passed_time":0.524901861,"remaining_time":10.41055358},
{"learn":[0.3961199097],"iteration":48,"passed_time":0.5412602071,"remaining_time":10.50486647},
{"learn":[0.395568315],"iteration":49,"passed_time":0.5486838528,"remaining_time":10.4249932},
{"learn":[0.3948065313],"iteration":50,"passed_time":0.556515356,"remaining_time":10.35555045},
{"learn":[0.3946430703],"iteration":51,"passed_time":0.5638776592,"remaining_time":10.27992348},
{"learn":[0.3938318267],"iteration":52,"passed_time":0.5718224976,"remaining_time":10.21728123},
{"learn":[0.3934137952],"iteration":53,"passed_time":0.5789964885,"remaining_time":10.14316071},
{"learn":[0.3929129442],"iteration":54,"passed_time":0.5861043028,"remaining_time":10.07033757},
{"learn":[0.3922152899],"iteration":55,"passed_time":0.5929976757,"remaining_time":9.996246534},
{"learn":[0.3913540518],"iteration":56,"passed_time":0.5995915665,"remaining_time":9.919558723},
{"learn":[0.3908357022],"iteration":57,"passed_time":0.6079864706,"remaining_time":9.874538885},
{"learn":[0.3906944042],"iteration":58,"passed_time":0.6159627535,"remaining_time":9.824083916},
{"learn":[0.3905801224],"iteration":59,"passed_time":0.6233388483,"remaining_time":9.765641957},
{"learn":[0.3904883309],"iteration":60,"passed_time":0.6315293618,"remaining_time":9.721410996},
{"learn":[0.3897269184],"iteration":61,"passed_time":0.6406000599,"remaining_time":9.691658971},
{"learn":[0.3896998708],"iteration":62,"passed_time":0.6494363384,"remaining_time":9.65907697},
{"learn":[0.3893149588],"iteration":63,"passed_time":0.6561392453,"remaining_time":9.596036463},
{"learn":[0.388804517],"iteration":64,"passed_time":0.6654625552,"remaining_time":9.57242291},
{"learn":[0.3884645702],"iteration":65,"passed_time":0.6824557005,"remaining_time":9.657782186},
{"learn":[0.3875721819],"iteration":66,"passed_time":0.6909202967,"remaining_time":9.621322938},
{"learn":[0.3864134729],"iteration":67,"passed_time":0.6987762967,"remaining_time":9.577345714},
{"learn":[0.3861045773],"iteration":68,"passed_time":0.7082483153,"remaining_time":9.556220022},
{"learn":[0.3851362555],"iteration":69,"passed_time":0.7275043163,"remaining_time":9.665414489},
{"learn":[0.384128368],"iteration":70,"passed_time":0.7361859522,"remaining_time":9.632630276},
{"learn":[0.3833304752],"iteration":71,"passed_time":0.7452916928,"remaining_time":9.605981818},
{"learn":[0.3830286232],"iteration":72,"passed_time":0.7562702045,"remaining_time":9.60359561},
{"learn":[0.3828165923],"iteration":73,"passed_time":0.7670081513,"remaining_time":9.597966866},
{"learn":[0.3828165916],"iteration":74,"passed_time":0.7757116384,"remaining_time":9.567110207},
{"learn":[0.3827692385],"iteration":75,"passed_time":0.7834126851,"remaining_time":9.524648961},
{"learn":[0.3826934924],"iteration":76,"passed_time":0.7914830383,"remaining_time":9.487517459},
{"learn":[0.3825833039],"iteration":77,"passed_time":0.7999239497,"remaining_time":9.455511303},
{"learn":[0.3818004816],"iteration":78,"passed_time":0.8084373706,"remaining_time":9.424947068},
{"learn":[0.3810675276],"iteration":79,"passed_time":0.8162421411,"remaining_time":9.386784623},
{"learn":[0.3805329784],"iteration":80,"passed_time":0.8260930979,"remaining_time":9.372587123},
{"learn":[0.3799454176],"iteration":81,"passed_time":0.8353262285,"remaining_time":9.351578997},
{"learn":[0.3799045252],"iteration":82,"passed_time":0.8438992584,"remaining_time":9.323561686},
{"learn":[0.3796351694],"iteration":83,"passed_time":0.8545240704,"remaining_time":9.31838153},
{"learn":[0.378977869],"iteration":84,"passed_time":0.8640751154,"remaining_time":9.301514477},
{"learn":[0.3783857485],"iteration":85,"passed_time":0.8728197585,"remaining_time":9.2762472},
{"learn":[0.3781022757],"iteration":86,"passed_time":0.8808586473,"remaining_time":9.243953391},
{"learn":[0.3774368706],"iteration":87,"passed_time":0.8884743453,"remaining_time":9.207825033},
{"learn":[0.3770505327],"iteration":88,"passed_time":0.8960065848,"remaining_time":9.171483132},
{"learn":[0.3770504668],"iteration":89,"passed_time":0.9106243892,"remaining_time":9.20742438},
{"learn":[0.3768843757],"iteration":90,"passed_time":0.917870389,"remaining_time":9.168617402},
{"learn":[0.3757451314],"iteration":91,"passed_time":0.9260299112,"remaining_time":9.139512602},
{"learn":[0.3755026096],"iteration":92,"passed_time":0.9339270271,"remaining_time":9.108299071},
{"learn":[0.375151252],"iteration":93,"passed_time":0.9421504987,"remaining_time":9.080727147},
{"learn":[0.3751202161],"iteration":94,"passed_time":0.9514041158,"remaining_time":9.06337605},
{"learn":[0.3743950005],"iteration":95,"passed_time":0.9605564754,"remaining_time":9.045240143},
{"learn":[0.3743949124],"iteration":96,"passed_time":0.9702717654,"remaining_time":9.03252994},
{"learn":[0.3739762536],"iteration":97,"passed_time":0.9789053782,"remaining_time":9.009925011},
{"learn":[0.3737658799],"iteration":98,"passed_time":0.9888626356,"remaining_time":8.999648835},
{"learn":[0.3732077989],"iteration":99,"passed_time":0.995992513,"remaining_time":8.963932617},
{"learn":[0.3731039598],"iteration":100,"passed_time":1.007878762,"remaining_time":8.971118884},
{"learn":[0.3719379107],"iteration":101,"passed_time":1.017529963,"remaining_time":8.958253987},
{"learn":[0.3718602813],"iteration":102,"passed_time":1.028701939,"remaining_time":8.958695527},
{"learn":[0.3716032244],"iteration":103,"passed_time":1.040184914,"remaining_time":8.961593106},
{"learn":[0.3716032202],"iteration":104,"passed_time":1.049104306,"remaining_time":8.942365275},
{"learn":[0.3712398613],"iteration":105,"passed_time":1.057987355,"remaining_time":8.923025426},
{"learn":[0.3710659834],"iteration":106,"passed_time":1.06644298,"remaining_time":8.900313841},
{"learn":[0.3707901581],"iteration":107,"passed_time":1.074174749,"remaining_time":8.871887738},
{"learn":[0.3701423745],"iteration":108,"passed_time":1.08525974,"remaining_time":8.871251633},
{"learn":[0.3699552281],"iteration":109,"passed_time":1.093790682,"remaining_time":8.849760974},
{"learn":[0.3698951522],"iteration":110,"passed_time":1.11497379,"remaining_time":8.929835132},
{"learn":[0.3683822967],"iteration":111,"passed_time":1.122080032,"remaining_time":8.896491686},
{"learn":[0.3682310381],"iteration":112,"passed_time":1.13786755,"remaining_time":8.931756783},
{"learn":[0.3682310346],"iteration":113,"passed_time":1.145175234,"remaining_time":8.900221555},
{"learn":[0.3681635896],"iteration":114,"passed_time":1.16152046,"remaining_time":8.938657453},
{"learn":[0.3680287746],"iteration":115,"passed_time":1.194189729,"remaining_time":9.10054931},
{"learn":[0.367861153],"iteration":116,"passed_time":1.216486378,"remaining_time":9.180833093},
{"learn":[0.3677199687],"iteration":117,"passed_time":1.266538265,"remaining_time":9.466836864},
{"learn":[0.3670759571],"iteration":118,"passed_time":1.290080013,"remaining_time":9.550928501},
{"learn":[0.3669593473],"iteration":119,"passed_time":1.311476572,"remaining_time":9.61749486},
{"learn":[0.3663303125],"iteration":120,"passed_time":1.323795868,"remaining_time":9.616665853},
{"learn":[0.3658979689],"iteration":121,"passed_time":1.343657608,"remaining_time":9.669929341},
{"learn":[0.3658094614],"iteration":122,"passed_time":1.361452802,"remaining_time":9.707269167},
{"learn":[0.3658053746],"iteration":123,"passed_time":1.369450765,"remaining_time":9.674507018},
{"learn":[0.3654112848],"iteration":124,"passed_time":1.377571166,"remaining_time":9.642998159},
{"learn":[0.3649614608],"iteration":125,"passed_time":1.385605583,"remaining_time":9.611264126},
{"learn":[0.3649557741],"iteration":126,"passed_time":1.393325374,"remaining_time":9.577740564},
{"learn":[0.3644262419],"iteration":127,"passed_time":1.400428098,"remaining_time":9.540416417},
{"learn":[0.3643624976],"iteration":128,"passed_time":1.407370386,"remaining_time":9.502477568},
{"learn":[0.3643223528],"iteration":129,"passed_time":1.414146574,"remaining_time":9.463903993},
{"learn":[0.3638637516],"iteration":130,"passed_time":1.421315303,"remaining_time":9.428419833},
{"learn":[0.3638406074],"iteration":131,"passed_time":1.428882726,"remaining_time":9.395986412},
{"learn":[0.3636332561],"iteration":132,"passed_time":1.43746104,"remaining_time":9.370516703},
{"learn":[0.3635988419],"iteration":133,"passed_time":1.446462536,"remaining_time":9.348033999},
{"learn":[0.3633890694],"iteration":134,"passed_time":1.456535173,"remaining_time":9.332614254},
{"learn":[0.3632634968],"iteration":135,"passed_time":1.466154507,"remaining_time":9.314393339},
{"learn":[0.3632272888],"iteration":136,"passed_time":1.472941501,"remaining_time":9.278456314},
{"learn":[0.3623910893],"iteration":137,"passed_time":1.479655885,"remaining_time":9.242488211},
{"learn":[0.3622357601],"iteration":138,"passed_time":1.487348411,"remaining_time":9.212999867},
{"learn":[0.3620098835],"iteration":139,"passed_time":1.494053692,"remaining_time":9.177758397},
{"learn":[0.361807975],"iteration":140,"passed_time":1.501672486,"remaining_time":9.148486991},
{"learn":[0.3617702635],"iteration":141,"passed_time":1.508209995,"remaining_time":9.112987152},
{"learn":[0.3616275908],"iteration":142,"passed_time":1.544410103,"remaining_time":9.25566055},
{"learn":[0.3615027571],"iteration":143,"passed_time":1.551994067,"remaining_time":9.22574251},
{"learn":[0.3611929663],"iteration":144,"passed_time":1.559375453,"remaining_time":9.194938018},
{"learn":[0.3607295924],"iteration":145,"passed_time":1.566741905,"remaining_time":9.164367033},
{"learn":[0.3602285531],"iteration":146,"passed_time":1.574043445,"remaining_time":9.133735092},
{"learn":[0.360206104],"iteration":147,"passed_time":1.580930683,"remaining_time":9.101033391},
{"learn":[0.359236602],"iteration":148,"passed_time":1.587632527,"remaining_time":9.067619331},
{"learn":[0.3591319368],"iteration":149,"passed_time":1.596414508,"remaining_time":9.046348879},
{"learn":[0.3591268585],"iteration":150,"passed_time":1.603876494,"remaining_time":9.017822143},
{"learn":[0.3587219807],"iteration":151,"passed_time":1.610890821,"remaining_time":8.987075108},
{"learn":[0.3585579549],"iteration":152,"passed_time":1.617811949,"remaining_time":8.95612236},
{"learn":[0.3585304166],"iteration":153,"passed_time":1.62526339,"remaining_time":8.928394988},
{"learn":[0.3582132685],"iteration":154,"passed_time":1.631615154,"remaining_time":8.894934225},
{"learn":[0.3580823914],"iteration":155,"passed_time":1.651457448,"remaining_time":8.934808245},
{"learn":[0.3580193396],"iteration":156,"passed_time":1.66718327,"remaining_time":8.95181845},
{"learn":[0.3579330451],"iteration":157,"passed_time":1.674596692,"remaining_time":8.92411655},
{"learn":[0.357825201],"iteration":158,"passed_time":1.683555026,"remaining_time":8.904841362},
{"learn":[0.3566474882],"iteration":159,"passed_time":1.691066077,"remaining_time":8.878096903},
{"learn":[0.3565497096],"iteration":160,"passed_time":1.699385393,"remaining_time":8.855803384},
{"learn":[0.3565148713],"iteration":161,"passed_time":1.707479522,"remaining_time":8.832517528},
{"learn":[0.3563221886],"iteration":162,"passed_time":1.717027258,"remaining_time":8.816882301},
{"learn":[0.3562937622],"iteration":163,"passed_time":1.725595269,"remaining_time":8.796327103},
{"learn":[0.3562708556],"iteration":164,"passed_time":1.73510234,"remaining_time":8.780669415},
{"learn":[0.3559814966],"iteration":165,"passed_time":1.743443487,"remaining_time":8.759228122},
{"learn":[0.3556981339],"iteration":166,"passed_time":1.751790337,"remaining_time":8.737972162},
{"learn":[0.3556687592],"iteration":167,"passed_time":1.758566285,"remaining_time":8.709090173},
{"learn":[0.3556143977],"iteration":168,"passed_time":1.766806327,"remaining_time":8.68766898},
{"learn":[0.3555808199],"iteration":169,"passed_time":1.774183613,"remaining_time":8.66219058},
{"learn":[0.3553673623],"iteration":170,"passed_time":1.781605275,"remaining_time":8.637139024},
{"learn":[0.3552915051],"iteration":171,"passed_time":1.788206052,"remaining_time":8.608340763},
{"learn":[0.3552805551],"iteration":172,"passed_time":1.795222905,"remaining_time":8.581788105},
{"learn":[0.355245338],"iteration":173,"passed_time":1.802542056,"remaining_time":8.556895049},
{"learn":[0.3552376685],"iteration":174,"passed_time":1.810323552,"remaining_time":8.534382458},
{"learn":[0.3550572247],"iteration":175,"passed_time":1.817034076,"remaining_time":8.507023174},
{"learn":[0.3549451754],"iteration":176,"passed_time":1.824769926,"remaining_time":8.484664683},
{"learn":[0.3541722333],"iteration":177,"passed_time":1.854855276,"remaining_time":8.565679981},
{"learn":[0.3540769999],"iteration":178,"passed_time":1.862663864,"remaining_time":8.543279512},
{"learn":[0.3538341048],"iteration":179,"passed_time":1.872388166,"remaining_time":8.52976831},
{"learn":[0.353495686],"iteration":180,"passed_time":1.881208677,"remaining_time":8.512209426},
{"learn":[0.3530850267],"iteration":181,"passed_time":1.890526143,"remaining_time":8.496980139},
{"learn":[0.3530198237],"iteration":182,"passed_time":1.897415316,"remaining_time":8.470974391},
{"learn":[0.3527657062],"iteration":183,"passed_time":1.934371859,"remaining_time":8.578518678},
{"learn":[0.3525194147],"iteration":184,"passed_time":1.941009151,"remaining_time":8.550932207},
{"learn":[0.3524275022],"iteration":185,"passed_time":1.948351368,"remaining_time":8.526655986},
{"learn":[0.3522740769],"iteration":186,"passed_time":1.956851647,"remaining_time":8.507595664},
{"learn":[0.3520486063],"iteration":187,"passed_time":1.964722442,"remaining_time":8.485928847},
{"learn":[0.3520249553],"iteration":188,"passed_time":1.971623132,"remaining_time":8.460245291},
{"learn":[0.3514537665],"iteration":189,"passed_time":1.978363347,"remaining_time":8.434075322},
{"learn":[0.351120805],"iteration":190,"passed_time":1.986114381,"remaining_time":8.412390232},
{"learn":[0.3510092475],"iteration":191,"passed_time":1.993369192,"remaining_time":8.388762014},
{"learn":[0.3509266314],"iteration":192,"passed_time":2.001451552,"remaining_time":8.368763745},
{"learn":[0.3508888171],"iteration":193,"passed_time":2.010651933,"remaining_time":8.353533289},
{"learn":[0.350791918],"iteration":194,"passed_time":2.017611612,"remaining_time":8.329114601},
{"learn":[0.3507742186],"iteration":195,"passed_time":2.024616265,"remaining_time":8.305058558},
{"learn":[0.3507019092],"iteration":196,"passed_time":2.032181834,"remaining_time":8.283461995},
{"learn":[0.3504965859],"iteration":197,"passed_time":2.039355486,"remaining_time":8.260419695},
{"learn":[0.3500439829],"iteration":198,"passed_time":2.048142579,"remaining_time":8.244031185},
{"learn":[0.3490744036],"iteration":199,"passed_time":2.055075944,"remaining_time":8.220303778},
{"learn":[0.3490494752],"iteration":200,"passed_time":2.062717923,"remaining_time":8.199560299},
{"learn":[0.3489050547],"iteration":201,"passed_time":2.070259736,"remaining_time":8.178550838},
{"learn":[0.3487114186],"iteration":202,"passed_time":2.078823315,"remaining_time":8.161685626},
{"learn":[0.3486114647],"iteration":203,"passed_time":2.087337298,"remaining_time":8.14470828},
{"learn":[0.3485396738],"iteration":204,"passed_time":2.094799495,"remaining_time":8.123734627},
{"learn":[0.3485170494],"iteration":205,"passed_time":2.102611892,"remaining_time":8.104241954},
{"learn":[0.3476130408],"iteration":206,"passed_time":2.11137539,"remaining_time":8.088505721},
{"learn":[0.3475379313],"iteration":207,"passed_time":2.120716844,"remaining_time":8.075037212},
{"learn":[0.347483635],"iteration":208,"passed_time":2.137141215,"remaining_time":8.088414837},
{"learn":[0.3472262961],"iteration":209,"passed_time":2.145569515,"remaining_time":8.071428177},
{"learn":[0.3471922211],"iteration":210,"passed_time":2.153144146,"remaining_time":8.05133048},
{"learn":[0.3468375339],"iteration":211,"passed_time":2.160756404,"remaining_time":8.031490785},
{"learn":[0.3467355229],"iteration":212,"passed_time":2.168943911,"remaining_time":8.013891353},
{"learn":[0.346715142],"iteration":213,"passed_time":2.176652987,"remaining_time":7.994622653},
{"learn":[0.346614059],"iteration":214,"passed_time":2.183219263,"remaining_time":7.971288936},
{"learn":[0.3458009638],"iteration":215,"passed_time":2.190511681,"remaining_time":7.950746103},
{"learn":[0.3457611954],"iteration":216,"passed_time":2.197086217,"remaining_time":7.927735059},
{"learn":[0.3456716939],"iteration":217,"passed_time":2.205204793,"remaining_time":7.910413522},
{"learn":[0.3455363981],"iteration":218,"passed_time":2.212988052,"remaining_time":7.891980222},
{"learn":[0.3455019627],"iteration":219,"passed_time":2.221285116,"remaining_time":7.875465412},
{"learn":[0.3450524851],"iteration":220,"passed_time":2.227941654,"remaining_time":7.8532423},
{"learn":[0.345021814],"iteration":221,"passed_time":2.235001227,"remaining_time":7.832571868},
{"learn":[0.3442728558],"iteration":222,"passed_time":2.241558481,"remaining_time":7.810273273},
{"learn":[0.3442212162],"iteration":223,"passed_time":2.249356014,"remaining_time":7.792411906},
{"learn":[0.3440392387],"iteration":224,"passed_time":2.256625309,"remaining_time":7.772820507},
{"learn":[0.3439702231],"iteration":225,"passed_time":2.265779944,"remaining_time":7.759795028},
{"learn":[0.3437831141],"iteration":226,"passed_time":2.273551496,"remaining_time":7.742093859},
{"learn":[0.3434456669],"iteration":227,"passed_time":2.282112007,"remaining_time":7.727151183},
{"learn":[0.3433848312],"iteration":228,"passed_time":2.290456483,"remaining_time":7.711536892},
{"learn":[0.343202053],"iteration":229,"passed_time":2.299813033,"remaining_time":7.699374065},
{"learn":[0.3430631421],"iteration":230,"passed_time":2.309363505,"remaining_time":7.687881105},
{"learn":[0.3428478125],"iteration":231,"passed_time":2.317966155,"remaining_time":7.673267271},
{"learn":[0.342371032],"iteration":232,"passed_time":2.326541563,"remaining_time":7.65861536},
{"learn":[0.3423586379],"iteration":233,"passed_time":2.33547888,"remaining_time":7.645200094},
{"learn":[0.3423241015],"iteration":234,"passed_time":2.343435184,"remaining_time":7.628629428},
{"learn":[0.3422452216],"iteration":235,"passed_time":2.352391223,"remaining_time":7.615368196},
{"learn":[0.3413587184],"iteration":236,"passed_time":2.360995107,"remaining_time":7.601009564},
{"learn":[0.3412957215],"iteration":237,"passed_time":2.368637436,"remaining_time":7.583620697},
{"learn":[0.3411202644],"iteration":238,"passed_time":2.376032405,"remaining_time":7.565525775},
{"learn":[0.3409848785],"iteration":239,"passed_time":2.385058467,"remaining_time":7.552685146},
{"learn":[0.3408213352],"iteration":240,"passed_time":2.393660196,"remaining_time":7.538539788},
{"learn":[0.3408097011],"iteration":241,"passed_time":2.40301483,"remaining_time":7.526798516},
{"learn":[0.3407103849],"iteration":242,"passed_time":2.412168804,"remaining_time":7.514451787},
{"learn":[0.3406142333],"iteration":243,"passed_time":2.421122869,"remaining_time":7.50151184},
{"learn":[0.3404249769],"iteration":244,"passed_time":2.430652352,"remaining_time":7.490377656},
{"learn":[0.3399697616],"iteration":245,"passed_time":2.439297281,"remaining_time":7.476545326},
{"learn":[0.3397961684],"iteration":246,"passed_time":2.449917473,"remaining_time":7.468776748},
{"learn":[0.3396392897],"iteration":247,"passed_time":2.458780053,"remaining_time":7.455655646},
{"learn":[0.3389250207],"iteration":248,"passed_time":2.46784213,"remaining_time":7.443170441},
{"learn":[0.3388749991],"iteration":249,"passed_time":2.477614975,"remaining_time":7.432844925},
{"learn":[0.3387567085],"iteration":250,"passed_time":2.484833229,"remaining_time":7.414900751},
{"learn":[0.3385029576],"iteration":251,"passed_time":2.492766029,"remaining_time":7.399162657},
{"learn":[0.338217847],"iteration":252,"passed_time":2.500064782,"remaining_time":7.381614199},
{"learn":[0.3379866173],"iteration":253,"passed_time":2.508582635,"remaining_time":7.367726953},
{"learn":[0.3379520413],"iteration":254,"passed_time":2.51647081,"remaining_time":7.352042169},
{"learn":[0.3375936636],"iteration":255,"passed_time":2.524971671,"remaining_time":7.33819892},
{"learn":[0.3371182438],"iteration":256,"passed_time":2.534258767,"remaining_time":7.326670286},
{"learn":[0.3369947474],"iteration":257,"passed_time":2.541268111,"remaining_time":7.308608289},
{"learn":[0.3368100349],"iteration":258,"passed_time":2.549743695,"remaining_time":7.294826555},
{"learn":[0.3367672293],"iteration":259,"passed_time":2.558933744,"remaining_time":7.283119116},
{"learn":[0.3366784645],"iteration":260,"passed_time":2.568375971,"remaining_time":7.272144992},
{"learn":[0.3366577278],"iteration":261,"passed_time":2.579144963,"remaining_time":7.264919781},
{"learn":[0.3360565824],"iteration":262,"passed_time":2.587486259,"remaining_time":7.250864537},
{"learn":[0.3360375494],"iteration":263,"passed_time":2.595395676,"remaining_time":7.235648551},
{"learn":[0.3360268746],"iteration":264,"passed_time":2.604696432,"remaining_time":7.224346708},
{"learn":[0.3359721986],"iteration":265,"passed_time":2.61173678,"remaining_time":7.206822543},
{"learn":[0.3356715681],"iteration":266,"passed_time":2.619107853,"remaining_time":7.190284854},
{"learn":[0.335557159],"iteration":267,"passed_time":2.626238241,"remaining_time":7.173158182},
{"learn":[0.3354865479],"iteration":268,"passed_time":2.633523864,"remaining_time":7.156527675},
{"learn":[0.3354161582],"iteration":269,"passed_time":2.640223413,"remaining_time":7.138381819},
{"learn":[0.3353779125],"iteration":270,"passed_time":2.652173242,"remaining_time":7.134443887},
{"learn":[0.3351517402],"iteration":271,"passed_time":2.66024594,"remaining_time":7.120070015},
{"learn":[0.3351066001],"iteration":272,"passed_time":2.666852932,"remaining_time":7.101839128},
{"learn":[0.3348211102],"iteration":273,"passed_time":2.674566006,"remaining_time":7.086623797},
{"learn":[0.3347030805],"iteration":274,"passed_time":2.6836393,"remaining_time":7.075049064},
{"learn":[0.3344460787],"iteration":275,"passed_time":2.692703273,"remaining_time":7.063468006},
{"learn":[0.334381831],"iteration":276,"passed_time":2.701185892,"remaining_time":7.050387725},
{"learn":[0.3340401586],"iteration":277,"passed_time":2.710238066,"remaining_time":7.038819726},
{"learn":[0.3339626183],"iteration":278,"passed_time":2.718387766,"remaining_time":7.024937559},
{"learn":[0.3339558809],"iteration":279,"passed_time":2.726649527,"remaining_time":7.011384498},
{"learn":[0.3338414169],"iteration":280,"passed_time":2.735053692,"remaining_time":6.998233468},
{"learn":[0.3338235699],"iteration":281,"passed_time":2.744575408,"remaining_time":6.9879615},
{"learn":[0.3337923931],"iteration":282,"passed_time":2.752257951,"remaining_time":6.973035163},
{"learn":[0.3337871795],"iteration":283,"passed_time":2.76193062,"remaining_time":6.963177198},
{"learn":[0.3335103013],"iteration":284,"passed_time":2.769329248,"remaining_time":6.947615483},
{"learn":[0.3333992593],"iteration":285,"passed_time":2.777304698,"remaining_time":6.933550889},
{"learn":[0.3327432292],"iteration":286,"passed_time":2.783555033,"remaining_time":6.915242992},
{"learn":[0.3327100832],"iteration":287,"passed_time":2.791000601,"remaining_time":6.899973708},
{"learn":[0.3325097204],"iteration":288,"passed_time":2.79877083,"remaining_time":6.885557302},
{"learn":[0.3322840372],"iteration":289,"passed_time":2.806712683,"remaining_time":6.871606912},
{"learn":[0.3322183976],"iteration":290,"passed_time":2.814104312,"remaining_time":6.856357242},
{"learn":[0.3319868595],"iteration":291,"passed_time":2.822584908,"remaining_time":6.843801764},
{"learn":[0.331851142],"iteration":292,"passed_time":2.830178242,"remaining_time":6.829133163},
{"learn":[0.33164504],"iteration":293,"passed_time":2.838892804,"remaining_time":6.81720517},
{"learn":[0.3313607736],"iteration":294,"passed_time":2.846354289,"remaining_time":6.802304319},
{"learn":[0.3312964833],"iteration":295,"passed_time":2.854116671,"remaining_time":6.78816938},
{"learn":[0.3310754606],"iteration":296,"passed_time":2.862271461,"remaining_time":6.775006185},
{"learn":[0.3309330857],"iteration":297,"passed_time":2.871745966,"remaining_time":6.764985463},
{"learn":[0.3306876297],"iteration":298,"passed_time":2.881423428,"remaining_time":6.755444223},
{"learn":[0.3306025681],"iteration":299,"passed_time":2.889928217,"remaining_time":6.743165841},
{"learn":[0.3305918743],"iteration":300,"passed_time":2.89929456,"remaining_time":6.732913281},
{"learn":[0.3305667269],"iteration":301,"passed_time":2.90675403,"remaining_time":6.718259315},
{"learn":[0.3305220444],"iteration":302,"passed_time":2.91413693,"remaining_time":6.703476701},
{"learn":[0.3299748403],"iteration":303,"passed_time":2.922270882,"remaining_time":6.690462281},
{"learn":[0.329885754],"iteration":304,"passed_time":2.930274718,"remaining_time":6.677183374},
{"learn":[0.3298678335],"iteration":305,"passed_time":2.937950336,"remaining_time":6.663194552},
{"learn":[0.3298557422],"iteration":306,"passed_time":2.945510282,"remaining_time":6.648985752},
{"learn":[0.3293311945],"iteration":307,"passed_time":2.954117322,"remaining_time":6.637172685},
{"learn":[0.3290373936],"iteration":308,"passed_time":2.96185731,"remaining_time":6.623441428},
{"learn":[0.3284912273],"iteration":309,"passed_time":2.968601734,"remaining_time":6.607532893},
{"learn":[0.3283201206],"iteration":310,"passed_time":2.976096366,"remaining_time":6.593345326},
{"learn":[0.3280724619],"iteration":311,"passed_time":2.982896902,"remaining_time":6.577670091},
{"learn":[0.3280426475],"iteration":312,"passed_time":2.990861918,"remaining_time":6.564607468},
{"learn":[0.3273892205],"iteration":313,"passed_time":2.998414015,"remaining_time":6.550675204},
{"learn":[0.327204489],"iteration":314,"passed_time":3.007541036,"remaining_time":6.540208284},
{"learn":[0.3270833086],"iteration":315,"passed_time":3.015319614,"remaining_time":6.526831063},
{"learn":[0.3270527091],"iteration":316,"passed_time":3.024566364,"remaining_time":6.516652451},
{"learn":[0.3270417159],"iteration":317,"passed_time":3.033777703,"remaining_time":6.506403753},
{"learn":[0.3269648977],"iteration":318,"passed_time":3.043056087,"remaining_time":6.496304688},
{"learn":[0.3268519029],"iteration":319,"passed_time":3.052516529,"remaining_time":6.486597623},
{"learn":[0.3266113662],"iteration":320,"passed_time":3.061272458,"remaining_time":6.475401866},
{"learn":[0.3263080543],"iteration":321,"passed_time":3.069850852,"remaining_time":6.463847446},
{"learn":[0.3261303084],"iteration":322,"passed_time":3.076828644,"remaining_time":6.448956632},
{"learn":[0.3260654247],"iteration":323,"passed_time":3.085799116,"remaining_time":6.438272229},
{"learn":[0.3259857906],"iteration":324,"passed_time":3.094681333,"remaining_time":6.427415077},
{"learn":[0.3255140681],"iteration":325,"passed_time":3.105348393,"remaining_time":6.420260175},
{"learn":[0.3254826969],"iteration":326,"passed_time":3.114054497,"remaining_time":6.40904794},
{"learn":[0.3254675662],"iteration":327,"passed_time":3.122524948,"remaining_time":6.397368186},
{"learn":[0.3253808382],"iteration":328,"passed_time":3.130191824,"remaining_time":6.384069039},
{"learn":[0.3253423455],"iteration":329,"passed_time":3.138310289,"remaining_time":6.37172089},
{"learn":[0.3253174827],"iteration":330,"passed_time":3.145210528,"remaining_time":6.356936083},
{"learn":[0.3253026812],"iteration":331,"passed_time":3.153081063,"remaining_time":6.344151054},
{"learn":[0.3250961298],"iteration":332,"passed_time":3.162824468,"remaining_time":6.335146908},
{"learn":[0.32502301],"iteration":333,"passed_time":3.171490667,"remaining_time":6.323990373},
{"learn":[0.3246593866],"iteration":334,"passed_time":3.179645479,"remaining_time":6.311833562},
{"learn":[0.3244536973],"iteration":335,"passed_time":3.187620999,"remaining_time":6.29934626},
{"learn":[0.3244241217],"iteration":336,"passed_time":3.195570309,"remaining_time":6.286834169},
{"learn":[0.3244100896],"iteration":337,"passed_time":3.203507038,"remaining_time":6.274324435},
{"learn":[0.3243153894],"iteration":338,"passed_time":3.212046019,"remaining_time":6.263015984},
{"learn":[0.3241205457],"iteration":339,"passed_time":3.21881503,"remaining_time":6.248287999},
{"learn":[0.3241077418],"iteration":340,"passed_time":3.226016085,"remaining_time":6.234441642},
{"learn":[0.3240673194],"iteration":341,"passed_time":3.233097829,"remaining_time":6.220404595},
{"learn":[0.3239182156],"iteration":342,"passed_time":3.240019288,"remaining_time":6.206101084},
{"learn":[0.3238707278],"iteration":343,"passed_time":3.24650313,"remaining_time":6.191005969},
{"learn":[0.3238616013],"iteration":344,"passed_time":3.252713843,"remaining_time":6.175442224},
{"learn":[0.3238308516],"iteration":345,"passed_time":3.261218894,"remaining_time":6.16426924},
{"learn":[0.323804806],"iteration":346,"passed_time":3.268379344,"remaining_time":6.150581301},
{"learn":[0.3232425964],"iteration":347,"passed_time":3.275991753,"remaining_time":6.137777652},
{"learn":[0.3231888961],"iteration":348,"passed_time":3.282936507,"remaining_time":6.123758355},
{"learn":[0.3231317804],"iteration":349,"passed_time":3.291362173,"remaining_time":6.112529749},
{"learn":[0.3231071558],"iteration":350,"passed_time":3.301142835,"remaining_time":6.103822508},
{"learn":[0.3230724908],"iteration":351,"passed_time":3.309458523,"remaining_time":6.092412282},
{"learn":[0.3230611799],"iteration":352,"passed_time":3.319051135,"remaining_time":6.083360013},
{"learn":[0.3230082157],"iteration":353,"passed_time":3.326608455,"remaining_time":6.07059057},
{"learn":[0.3228172632],"iteration":354,"passed_time":3.333948776,"remaining_time":6.057456226},
{"learn":[0.3227987727],"iteration":355,"passed_time":3.341080718,"remaining_time":6.043977479},
{"learn":[0.3226702419],"iteration":356,"passed_time":3.348383061,"remaining_time":6.030841199},
{"learn":[0.3221674098],"iteration":357,"passed_time":3.35615381,"remaining_time":6.018577503},
{"learn":[0.3220767271],"iteration":358,"passed_time":3.363157452,"remaining_time":6.004969154},
{"learn":[0.3220398851],"iteration":359,"passed_time":3.37076131,"remaining_time":5.992464552},
{"learn":[0.3217529366],"iteration":360,"passed_time":3.377600627,"remaining_time":5.978633796},
{"learn":[0.3216680864],"iteration":361,"passed_time":3.385570704,"remaining_time":5.966834555},
{"learn":[0.3215997921],"iteration":362,"passed_time":3.392499892,"remaining_time":5.953229838},
{"learn":[0.321289166],"iteration":363,"passed_time":3.401511992,"remaining_time":5.943301172},
{"learn":[0.3212676194],"iteration":364,"passed_time":3.408682777,"remaining_time":5.930174146},
{"learn":[0.3212448999],"iteration":365,"passed_time":3.418594235,"remaining_time":5.921827171},
{"learn":[0.320838763],"iteration":366,"passed_time":3.424937928,"remaining_time":5.907318007},
{"learn":[0.3205618716],"iteration":367,"passed_time":3.431710067,"remaining_time":5.893589029},
{"learn":[0.3204440017],"iteration":368,"passed_time":3.438146218,"remaining_time":5.879323208},
{"learn":[0.3203451415],"iteration":369,"passed_time":3.445661519,"remaining_time":5.866937182},
{"learn":[0.3201996694],"iteration":370,"passed_time":3.454284357,"remaining_time":5.856455151},
{"learn":[0.3199380556],"iteration":371,"passed_time":3.463058129,"remaining_time":5.846237917},
{"learn":[0.3199130522],"iteration":372,"passed_time":3.472416613,"remaining_time":5.837011304},
{"learn":[0.3197969885],"iteration":373,"passed_time":3.481931853,"remaining_time":5.828046363},
{"learn":[0.3197838517],"iteration":374,"passed_time":3.488106059,"remaining_time":5.813510099},
{"learn":[0.3197435649],"iteration":375,"passed_time":3.496099261,"remaining_time":5.802037072},
{"learn":[0.3195583867],"iteration":376,"passed_time":3.503910767,"remaining_time":5.790282249},
{"learn":[0.3193328335],"iteration":377,"passed_time":3.511805647,"remaining_time":5.778685483},
{"learn":[0.3192137289],"iteration":378,"passed_time":3.519348794,"remaining_time":5.76653193},
{"learn":[0.3190287246],"iteration":379,"passed_time":3.527205145,"remaining_time":5.754913658},
{"learn":[0.3188603957],"iteration":380,"passed_time":3.533678864,"remaining_time":5.741068811},
{"learn":[0.3187354473],"iteration":381,"passed_time":3.541912249,"remaining_time":5.730109346},
{"learn":[0.3185417359],"iteration":382,"passed_time":3.549036493,"remaining_time":5.717377328},
{"learn":[0.3184222553],"iteration":383,"passed_time":3.556858844,"remaining_time":5.705794396},
{"learn":[0.318389798],"iteration":384,"passed_time":3.564250144,"remaining_time":5.693542439},
{"learn":[0.3183774173],"iteration":385,"passed_time":3.572585278,"remaining_time":5.682816997},
{"learn":[0.3183508477],"iteration":386,"passed_time":3.579383368,"remaining_time":5.669669262},
{"learn":[0.3180864988],"iteration":387,"passed_time":3.587015884,"remaining_time":5.657870415},
{"learn":[0.3179794521],"iteration":388,"passed_time":3.593749853,"remaining_time":5.644681646},
{"learn":[0.3179637611],"iteration":389,"passed_time":3.602008247,"remaining_time":5.633910335},
{"learn":[0.3178662783],"iteration":390,"passed_time":3.609957104,"remaining_time":5.62266976},
{"learn":[0.3174042249],"iteration":391,"passed_time":3.618651921,"remaining_time":5.61260298},
{"learn":[0.3172396014],"iteration":392,"passed_time":3.626112544,"remaining_time":5.600636932},
{"learn":[0.3172286549],"iteration":393,"passed_time":3.633701367,"remaining_time":5.588890935},
{"learn":[0.3172141618],"iteration":394,"passed_time":3.641054539,"remaining_time":5.576805053},
{"learn":[0.3171336639],"iteration":395,"passed_time":3.648011952,"remaining_time":5.564139442},
{"learn":[0.3167667007],"iteration":396,"passed_time":3.654742643,"remaining_time":5.551158222},
{"learn":[0.3167132764],"iteration":397,"passed_time":3.661248187,"remaining_time":5.537867861},
{"learn":[0.3165745309],"iteration":398,"passed_time":3.670533929,"remaining_time":5.528799226},
{"learn":[0.3165292603],"iteration":399,"passed_time":3.677479594,"remaining_time":5.516219391},
{"learn":[0.3163606567],"iteration":400,"passed_time":3.685964097,"remaining_time":5.50596632},
{"learn":[0.3161879595],"iteration":401,"passed_time":3.707152809,"remaining_time":5.514620348},
{"learn":[0.3161185479],"iteration":402,"passed_time":3.743096808,"remaining_time":5.544984602},
{"learn":[0.3158482558],"iteration":403,"passed_time":3.75121775,"remaining_time":5.5339747},
{"learn":[0.3158368941],"iteration":404,"passed_time":3.760217059,"remaining_time":5.524269507},
{"learn":[0.3158017555],"iteration":405,"passed_time":3.769773566,"remaining_time":5.515383001},
{"learn":[0.3153312424],"iteration":406,"passed_time":3.77865913,"remaining_time":5.505515637},
{"learn":[0.3153175105],"iteration":407,"passed_time":3.786915991,"remaining_time":5.494740849},
{"learn":[0.3152449082],"iteration":408,"passed_time":3.795473254,"remaining_time":5.484412453},
{"learn":[0.3151714485],"iteration":409,"passed_time":3.80290541,"remaining_time":5.472473639},
{"learn":[0.315133804],"iteration":410,"passed_time":3.810257449,"remaining_time":5.46044194},
{"learn":[0.3151092625],"iteration":411,"passed_time":3.820097661,"remaining_time":5.451984041},
{"learn":[0.315098874],"iteration":412,"passed_time":3.827365112,"remaining_time":5.439862762},
{"learn":[0.3144328631],"iteration":413,"passed_time":3.834659936,"remaining_time":5.427803677},
{"learn":[0.3143316532],"iteration":414,"passed_time":3.842357925,"remaining_time":5.416335871},
{"learn":[0.3142760659],"iteration":415,"passed_time":3.849273632,"remaining_time":5.403787983},
{"learn":[0.3139865184],"iteration":416,"passed_time":3.857468626,"remaining_time":5.393055656},
{"learn":[0.3138343349],"iteration":417,"passed_time":3.866447158,"remaining_time":5.383426425},
{"learn":[0.3137786216],"iteration":418,"passed_time":3.874047277,"remaining_time":5.371888945},
{"learn":[0.3137498259],"iteration":419,"passed_time":3.882495927,"remaining_time":5.361541995},
{"learn":[0.3137353636],"iteration":420,"passed_time":3.897269045,"remaining_time":5.359902084},
{"learn":[0.3137075741],"iteration":421,"passed_time":3.904570094,"remaining_time":5.347965674},
{"learn":[0.3136911726],"iteration":422,"passed_time":3.91160116,"remaining_time":5.335682907},
{"learn":[0.3136779683],"iteration":423,"passed_time":3.918887885,"remaining_time":5.323772221},
{"learn":[0.3134864267],"iteration":424,"passed_time":3.925357555,"remaining_time":5.310777869},
{"learn":[0.3134437514],"iteration":425,"passed_time":3.933592463,"remaining_time":5.300192662},
{"learn":[0.3133894254],"iteration":426,"passed_time":3.942316309,"remaining_time":5.290274578},
{"learn":[0.3128478777],"iteration":427,"passed_time":3.950694804,"remaining_time":5.279900532},
{"learn":[0.3123033695],"iteration":428,"passed_time":3.959392277,"remaining_time":5.26996035},
{"learn":[0.3122632873],"iteration":429,"passed_time":3.969248166,"remaining_time":5.261561522},
{"learn":[0.3120182728],"iteration":430,"passed_time":3.976301263,"remaining_time":5.249455727},
{"learn":[0.3119711424],"iteration":431,"passed_time":3.98452267,"remaining_time":5.238909436},
{"learn":[0.3119005383],"iteration":432,"passed_time":3.992416218,"remaining_time":5.227944562},
{"learn":[0.3116487024],"iteration":433,"passed_time":4.001294074,"remaining_time":5.218277524},
{"learn":[0.3111771736],"iteration":434,"passed_time":4.008907474,"remaining_time":5.206971777},
{"learn":[0.3111046065],"iteration":435,"passed_time":4.017708209,"remaining_time":5.197218876},
{"learn":[0.3110947147],"iteration":436,"passed_time":4.026806122,"remaining_time":5.187853196},
{"learn":[0.3110844426],"iteration":437,"passed_time":4.035097052,"remaining_time":5.177453295},
{"learn":[0.31070129],"iteration":438,"passed_time":4.042978201,"remaining_time":5.166539341},
{"learn":[0.3104974838],"iteration":439,"passed_time":4.050226536,"remaining_time":5.154833773},
{"learn":[0.3096549132],"iteration":440,"passed_time":4.058121868,"remaining_time":5.143968536},
{"learn":[0.3096129545],"iteration":441,"passed_time":4.067558765,"remaining_time":5.135062876},
{"learn":[0.3093949404],"iteration":442,"passed_time":4.074951709,"remaining_time":5.12358488},
{"learn":[0.309202195],"iteration":443,"passed_time":4.083391098,"remaining_time":5.113435699},
{"learn":[0.3090909015],"iteration":444,"passed_time":4.091801477,"remaining_time":5.103258022},
{"learn":[0.3090765852],"iteration":445,"passed_time":4.100364314,"remaining_time":5.093277646},
{"learn":[0.3089853092],"iteration":446,"passed_time":4.10800915,"remaining_time":5.082167919},
{"learn":[0.3089266872],"iteration":447,"passed_time":4.115843359,"remaining_time":5.071306995},
{"learn":[0.3088547518],"iteration":448,"passed_time":4.151206404,"remaining_time":5.094242157},
{"learn":[0.3086399234],"iteration":449,"passed_time":4.158179263,"remaining_time":5.082219099},
{"learn":[0.3082860202],"iteration":450,"passed_time":4.166986383,"remaining_time":5.072451274},
{"learn":[0.3077137961],"iteration":451,"passed_time":4.194877419,"remaining_time":5.085824836},
{"learn":[0.3076738468],"iteration":452,"passed_time":4.203801234,"remaining_time":5.07611319},
{"learn":[0.3075104863],"iteration":453,"passed_time":4.211377458,"remaining_time":5.064784344},
{"learn":[0.3074288909],"iteration":454,"passed_time":4.218759057,"remaining_time":5.05323887},
{"learn":[0.3074214084],"iteration":455,"passed_time":4.226178252,"remaining_time":5.041756511},
{"learn":[0.3072404418],"iteration":456,"passed_time":4.242707608,"remaining_time":5.04111648},
{"learn":[0.3072338423],"iteration":457,"passed_time":4.251113437,"remaining_time":5.030793631},
{"learn":[0.3070724864],"iteration":458,"passed_time":4.272726514,"remaining_time":5.036045847},
{"learn":[0.3069312567],"iteration":459,"passed_time":4.2818645,"remaining_time":5.026536586},
{"learn":[0.3068997],"iteration":460,"passed_time":4.290915773,"remaining_time":5.016927552},
{"learn":[0.3067287241],"iteration":461,"passed_time":4.308973122,"remaining_time":5.017808527},
{"learn":[0.3064177478],"iteration":462,"passed_time":4.317576714,"remaining_time":5.007642971},
{"learn":[0.3060521939],"iteration":463,"passed_time":4.326615969,"remaining_time":4.997987412},
{"learn":[0.3057956776],"iteration":464,"passed_time":4.334353711,"remaining_time":4.986837066},
{"learn":[0.3057734401],"iteration":465,"passed_time":4.341977707,"remaining_time":4.975571021},
{"learn":[0.3057625327],"iteration":466,"passed_time":4.348989959,"remaining_time":4.963622373},
{"learn":[0.3057494143],"iteration":467,"passed_time":4.356992362,"remaining_time":4.952820377},
{"learn":[0.305749332],"iteration":468,"passed_time":4.364199511,"remaining_time":4.941129937},
{"learn":[0.305569204],"iteration":469,"passed_time":4.371970231,"remaining_time":4.93009409},
{"learn":[0.3052703293],"iteration":470,"passed_time":4.380275233,"remaining_time":4.919672183},
{"learn":[0.3051835294],"iteration":471,"passed_time":4.388881483,"remaining_time":4.909596235},
{"learn":[0.3049018613],"iteration":472,"passed_time":4.397612605,"remaining_time":4.89966563},
{"learn":[0.3048915612],"iteration":473,"passed_time":4.406691502,"remaining_time":4.890126013},
{"learn":[0.3048100044],"iteration":474,"passed_time":4.415696496,"remaining_time":4.880506654},
{"learn":[0.3047944384],"iteration":475,"passed_time":4.423867505,"remaining_time":4.869971791},
{"learn":[0.3040586],"iteration":476,"passed_time":4.433922822,"remaining_time":4.861512864},
{"learn":[0.3040460053],"iteration":477,"passed_time":4.441264847,"remaining_time":4.850084205},
{"learn":[0.3039885571],"iteration":478,"passed_time":4.450807624,"remaining_time":4.84106633},
{"learn":[0.3039789759],"iteration":479,"passed_time":4.459111381,"remaining_time":4.830703997},
{"learn":[0.3037526697],"iteration":480,"passed_time":4.46758541,"remaining_time":4.820533946},
{"learn":[0.3035872629],"iteration":481,"passed_time":4.475123926,"remaining_time":4.809365547},
{"learn":[0.3035584204],"iteration":482,"passed_time":4.526775744,"remaining_time":4.845430765},
{"learn":[0.3035460328],"iteration":483,"passed_time":4.533845782,"remaining_time":4.833604181},
{"learn":[0.3034524144],"iteration":484,"passed_time":4.542346483,"remaining_time":4.823316369},
{"learn":[0.3033777098],"iteration":485,"passed_time":4.549724373,"remaining_time":4.811848411},
{"learn":[0.3033585552],"iteration":486,"passed_time":4.55714062,"remaining_time":4.800437656},
{"learn":[0.3033484113],"iteration":487,"passed_time":4.565056772,"remaining_time":4.789567761},
{"learn":[0.3030655114],"iteration":488,"passed_time":4.573139032,"remaining_time":4.778883529},
{"learn":[0.3029375164],"iteration":489,"passed_time":4.582335546,"remaining_time":4.76936965},
{"learn":[0.3029258984],"iteration":490,"passed_time":4.589392693,"remaining_time":4.757639268},
{"learn":[0.3026666706],"iteration":491,"passed_time":4.597102159,"remaining_time":4.746601417},
{"learn":[0.3026561818],"iteration":492,"passed_time":4.603933446,"remaining_time":4.73467395},
{"learn":[0.3024730445],"iteration":493,"passed_time":4.611278779,"remaining_time":4.723293649},
{"learn":[0.3023005832],"iteration":494,"passed_time":4.618657079,"remaining_time":4.711963283},
{"learn":[0.3019543607],"iteration":495,"passed_time":4.626629532,"remaining_time":4.701252589},
{"learn":[0.3017618802],"iteration":496,"passed_time":4.633819661,"remaining_time":4.689761146},
{"learn":[0.3016917307],"iteration":497,"passed_time":4.642770899,"remaining_time":4.680062232},
{"learn":[0.3016745167],"iteration":498,"passed_time":4.65052922,"remaining_time":4.669168616},
{"learn":[0.3016643311],"iteration":499,"passed_time":4.6583893,"remaining_time":4.6583893},
{"learn":[0.3016060139],"iteration":500,"passed_time":4.666815065,"remaining_time":4.648185065},
{"learn":[0.3015184927],"iteration":501,"passed_time":4.676283356,"remaining_time":4.639022134},
{"learn":[0.3012290568],"iteration":502,"passed_time":4.684697906,"remaining_time":4.628816817},
{"learn":[0.3012122773],"iteration":503,"passed_time":4.693155075,"remaining_time":4.61866055},
{"learn":[0.3011234251],"iteration":504,"passed_time":4.748682842,"remaining_time":4.654649518},
{"learn":[0.3008897429],"iteration":505,"passed_time":4.756683391,"remaining_time":4.64387667},
{"learn":[0.3008616547],"iteration":506,"passed_time":4.764808682,"remaining_time":4.633236056},
{"learn":[0.3004224361],"iteration":507,"passed_time":4.77215205,"remaining_time":4.621848049},
{"learn":[0.3003253216],"iteration":508,"passed_time":4.780530485,"remaining_time":4.611474397},
{"learn":[0.3003096185],"iteration":509,"passed_time":4.789312236,"remaining_time":4.60149607},
{"learn":[0.3001156498],"iteration":510,"passed_time":4.800222176,"remaining_time":4.593558991},
{"learn":[0.299929861],"iteration":511,"passed_time":4.806866686,"remaining_time":4.58154481},
{"learn":[0.2999264506],"iteration":512,"passed_time":4.814054178,"remaining_time":4.570067027},
{"learn":[0.2998827451],"iteration":513,"passed_time":4.823802525,"remaining_time":4.561027291},
{"learn":[0.2998725992],"iteration":514,"passed_time":4.831948836,"remaining_time":4.550476088},
{"learn":[0.299753834],"iteration":515,"passed_time":4.839643589,"remaining_time":4.539510653},
{"learn":[0.2997538299],"iteration":516,"passed_time":4.849021828,"remaining_time":4.530130644},
{"learn":[0.2997276027],"iteration":517,"passed_time":4.857086767,"remaining_time":4.519528613},
{"learn":[0.299698552],"iteration":518,"passed_time":4.865634659,"remaining_time":4.509383952},
{"learn":[0.2996824362],"iteration":519,"passed_time":4.874385588,"remaining_time":4.49943285},
{"learn":[0.299562891],"iteration":520,"passed_time":4.882079277,"remaining_time":4.488514345},
{"learn":[0.299554102],"iteration":521,"passed_time":4.890646915,"remaining_time":4.478408478},
{"learn":[0.2992564367],"iteration":522,"passed_time":4.900354237,"remaining_time":4.469347937},
{"learn":[0.2991016279],"iteration":523,"passed_time":4.908807517,"remaining_time":4.45914576},
{"learn":[0.2986428909],"iteration":524,"passed_time":4.915707856,"remaining_time":4.447545203},
{"learn":[0.2986345316],"iteration":525,"passed_time":4.925184667,"remaining_time":4.438284281},
{"learn":[0.2984040604],"iteration":526,"passed_time":4.935146774,"remaining_time":4.429458111},
{"learn":[0.2979730874],"iteration":527,"passed_time":4.942850408,"remaining_time":4.418608698},
{"learn":[0.2978742675],"iteration":528,"passed_time":4.951178194,"remaining_time":4.408326899},
{"learn":[0.2977748058],"iteration":529,"passed_time":4.959157123,"remaining_time":4.397743109},
{"learn":[0.2977624104],"iteration":530,"passed_time":4.967627603,"remaining_time":4.387603288},
{"learn":[0.2977532426],"iteration":531,"passed_time":4.976559497,"remaining_time":4.377875647},
{"learn":[0.2977325335],"iteration":532,"passed_time":4.986792539,"remaining_time":4.369291024},
{"learn":[0.2975886242],"iteration":533,"passed_time":4.99472557,"remaining_time":4.3586931},
{"learn":[0.2972098105],"iteration":534,"passed_time":5.001851267,"remaining_time":4.347403438},
{"learn":[0.2969323739],"iteration":535,"passed_time":5.008432318,"remaining_time":4.335657827},
{"learn":[0.2968980443],"iteration":536,"passed_time":5.017561333,"remaining_time":4.3261283},
{"learn":[0.2968567728],"iteration":537,"passed_time":5.025754122,"remaining_time":4.31579629},
{"learn":[0.2968455531],"iteration":538,"passed_time":5.034533347,"remaining_time":4.305973791},
{"learn":[0.2967040526],"iteration":539,"passed_time":5.042381789,"remaining_time":4.295362265},
{"learn":[0.2966255152],"iteration":540,"passed_time":5.050448974,"remaining_time":4.284946542},
{"learn":[0.2964680301],"iteration":541,"passed_time":5.058240163,"remaining_time":4.274306263},
{"learn":[0.2962933604],"iteration":542,"passed_time":5.066160935,"remaining_time":4.263785538},
{"learn":[0.2962530145],"iteration":543,"passed_time":5.073323198,"remaining_time":4.252638563},
{"learn":[0.2962341694],"iteration":544,"passed_time":5.082464592,"remaining_time":4.243158513},
{"learn":[0.2959435062],"iteration":545,"passed_time":5.090836371,"remaining_time":4.233039767},
{"learn":[0.2957154895],"iteration":546,"passed_time":5.098920636,"remaining_time":4.222689302},
{"learn":[0.2953357049],"iteration":547,"passed_time":5.105997249,"remaining_time":4.211515979},
{"learn":[0.2952103755],"iteration":548,"passed_time":5.115850161,"remaining_time":4.202638293},
{"learn":[0.2950178229],"iteration":549,"passed_time":5.124905494,"remaining_time":4.193104495},
{"learn":[0.294857005],"iteration":550,"passed_time":5.132174968,"remaining_time":4.18211717},
{"learn":[0.2947672483],"iteration":551,"passed_time":5.142208153,"remaining_time":4.173386327},
{"learn":[0.2947607659],"iteration":552,"passed_time":5.149432021,"remaining_time":4.162379952},
{"learn":[0.2946996587],"iteration":553,"passed_time":5.15676749,"remaining_time":4.151477077},
{"learn":[0.2946550473],"iteration":554,"passed_time":5.164453081,"remaining_time":4.140867785},
{"learn":[0.2945454783],"iteration":555,"passed_time":5.172672714,"remaining_time":4.130695476},
{"learn":[0.2943336447],"iteration":556,"passed_time":5.180205376,"remaining_time":4.119983809},
{"learn":[0.2937829786],"iteration":557,"passed_time":5.187306577,"remaining_time":4.108941769},
{"learn":[0.2937669276],"iteration":558,"passed_time":5.196545699,"remaining_time":4.099600453},
{"learn":[0.2937507548],"iteration":559,"passed_time":5.204866228,"remaining_time":4.089537751},
{"learn":[0.2936411511],"iteration":560,"passed_time":5.212337345,"remaining_time":4.078816568},
{"learn":[0.293610423],"iteration":561,"passed_time":5.221024825,"remaining_time":4.069054935},
{"learn":[0.2933410958],"iteration":562,"passed_time":5.23088718,"remaining_time":4.060209055},
{"learn":[0.2931609094],"iteration":563,"passed_time":5.2397451,"remaining_time":4.050583091},
{"learn":[0.2928747862],"iteration":564,"passed_time":5.248545924,"remaining_time":4.040915888},
{"learn":[0.2928305148],"iteration":565,"passed_time":5.256115021,"remaining_time":4.030307278},
{"learn":[0.2926626945],"iteration":566,"passed_time":5.263127454,"remaining_time":4.019284282},
{"learn":[0.2925083157],"iteration":567,"passed_time":5.271127061,"remaining_time":4.009026215},
{"learn":[0.2924995786],"iteration":568,"passed_time":5.278099508,"remaining_time":3.997998046},
{"learn":[0.2924939446],"iteration":569,"passed_time":5.287000539,"remaining_time":3.988439003},
{"learn":[0.2924249135],"iteration":570,"passed_time":5.29623867,"remaining_time":3.979135533},
{"learn":[0.2922953162],"iteration":571,"passed_time":5.303171294,"remaining_time":3.968107192},
{"learn":[0.2921547686],"iteration":572,"passed_time":5.310191425,"remaining_time":3.957158357},
{"learn":[0.2921204521],"iteration":573,"passed_time":5.316990025,"remaining_time":3.946058799},
{"learn":[0.2919644566],"iteration":574,"passed_time":5.324085262,"remaining_time":3.935193454},
{"learn":[0.2918144321],"iteration":575,"passed_time":5.330949246,"remaining_time":3.924170973},
{"learn":[0.2916400798],"iteration":576,"passed_time":5.337324355,"remaining_time":3.91280451},
{"learn":[0.2915587554],"iteration":577,"passed_time":5.345484907,"remaining_time":3.902758877},
{"learn":[0.2912189084],"iteration":578,"passed_time":5.355963216,"remaining_time":3.894405032},
{"learn":[0.2911810333],"iteration":579,"passed_time":5.363796934,"remaining_time":3.884128814},
{"learn":[0.2909109581],"iteration":580,"passed_time":5.370432021,"remaining_time":3.872996587},
{"learn":[0.2908779232],"iteration":581,"passed_time":5.378504168,"remaining_time":3.862911928},
{"learn":[0.2907320456],"iteration":582,"passed_time":5.387978311,"remaining_time":3.853836974},
{"learn":[0.2907170409],"iteration":583,"passed_time":5.395793317,"remaining_time":3.843578801},
{"learn":[0.2906093516],"iteration":584,"passed_time":5.402741307,"remaining_time":3.832713919},
{"learn":[0.2906001573],"iteration":585,"passed_time":5.409261796,"remaining_time":3.821560381},
{"learn":[0.290583802],"iteration":586,"passed_time":5.415477079,"remaining_time":3.810207894},
{"learn":[0.2905752606],"iteration":587,"passed_time":5.422756316,"remaining_time":3.799618371},
{"learn":[0.2905322621],"iteration":588,"passed_time":5.429305813,"remaining_time":3.788530881},
{"learn":[0.290526739],"iteration":589,"passed_time":5.436581041,"remaining_time":3.777963096},
{"learn":[0.2904684522],"iteration":590,"passed_time":5.443965025,"remaining_time":3.767481718},
{"learn":[0.2904555137],"iteration":591,"passed_time":5.45301757,"remaining_time":3.758160758},
{"learn":[0.2901566199],"iteration":592,"passed_time":5.460323521,"remaining_time":3.747641944},
{"learn":[0.2900571779],"iteration":593,"passed_time":5.466917271,"remaining_time":3.736647158},
{"learn":[0.2900167806],"iteration":594,"passed_time":5.474842303,"remaining_time":3.726573332},
{"learn":[0.290008788],"iteration":595,"passed_time":5.482125118,"remaining_time":3.716071389},
{"learn":[0.2897891191],"iteration":596,"passed_time":5.490112246,"remaining_time":3.70605567},
{"learn":[0.2897744416],"iteration":597,"passed_time":5.496661482,"remaining_time":3.695080127},
{"learn":[0.2894324268],"iteration":598,"passed_time":5.50392809,"remaining_time":3.684599606},
{"learn":[0.2893999377],"iteration":599,"passed_time":5.510507277,"remaining_time":3.673671518},
{"learn":[0.2893673987],"iteration":600,"passed_time":5.517034321,"remaining_time":3.662723284},
{"learn":[0.2890781603],"iteration":601,"passed_time":5.523575999,"remaining_time":3.651799415},
{"learn":[0.288912569],"iteration":602,"passed_time":5.530680337,"remaining_time":3.64126052},
{"learn":[0.288581991],"iteration":603,"passed_time":5.538982002,"remaining_time":3.631518002},
{"learn":[0.2884928204],"iteration":604,"passed_time":5.546566305,"remaining_time":3.621311885},
{"learn":[0.2884765209],"iteration":605,"passed_time":5.554223559,"remaining_time":3.611161852},
{"learn":[0.2883248179],"iteration":606,"passed_time":5.563122855,"remaining_time":3.601824188},
{"learn":[0.2882970451],"iteration":607,"passed_time":5.571061328,"remaining_time":3.591868488},
{"learn":[0.2879919304],"iteration":608,"passed_time":5.57874758,"remaining_time":3.581757477},
{"learn":[0.2879836314],"iteration":609,"passed_time":5.586576477,"remaining_time":3.571745616},
{"learn":[0.2879623443],"iteration":610,"passed_time":5.595072447,"remaining_time":3.5621656},
{"learn":[0.2879549136],"iteration":611,"passed_time":5.603959325,"remaining_time":3.552836958},
{"learn":[0.2878697759],"iteration":612,"passed_time":5.610887329,"remaining_time":3.542273077},
{"learn":[0.2874901518],"iteration":613,"passed_time":5.618275183,"remaining_time":3.532010131},
{"learn":[0.2874836272],"iteration":614,"passed_time":5.626191302,"remaining_time":3.522087238},
{"learn":[0.2871105773],"iteration":615,"passed_time":5.632914245,"remaining_time":3.511427062},
{"learn":[0.2871066868],"iteration":616,"passed_time":5.640002645,"remaining_time":3.501006504},
{"learn":[0.2871063725],"iteration":617,"passed_time":5.646736033,"remaining_time":3.490377289},
{"learn":[0.2870735015],"iteration":618,"passed_time":5.653528319,"remaining_time":3.479796913},
{"learn":[0.2864074563],"iteration":619,"passed_time":5.670025971,"remaining_time":3.475177208},
{"learn":[0.2862882661],"iteration":620,"passed_time":5.678270091,"remaining_time":3.465482068},
{"learn":[0.2862144389],"iteration":621,"passed_time":5.686393518,"remaining_time":3.455718247},
{"learn":[0.2861566277],"iteration":622,"passed_time":5.695246806,"remaining_time":3.446401358},
{"learn":[0.285889219],"iteration":623,"passed_time":5.70535612,"remaining_time":3.43784279},
{"learn":[0.2856736671],"iteration":624,"passed_time":5.714148455,"remaining_time":3.428489073},
{"learn":[0.2856689636],"iteration":625,"passed_time":5.721011456,"remaining_time":3.41798448},
{"learn":[0.2856590316],"iteration":626,"passed_time":5.728483787,"remaining_time":3.407853991},
{"learn":[0.2855176356],"iteration":627,"passed_time":5.737431416,"remaining_time":3.398605871},
{"learn":[0.2855112703],"iteration":628,"passed_time":5.744142702,"remaining_time":3.388039654},
{"learn":[0.2855001828],"iteration":629,"passed_time":5.751688225,"remaining_time":3.377975624},
{"learn":[0.2854130003],"iteration":630,"passed_time":5.758621251,"remaining_time":3.367561397},
{"learn":[0.2854095844],"iteration":631,"passed_time":5.765102508,"remaining_time":3.356895131},
{"learn":[0.2851831128],"iteration":632,"passed_time":5.772502418,"remaining_time":3.346774704},
{"learn":[0.2849209327],"iteration":633,"passed_time":5.779324915,"remaining_time":3.336329525},
{"learn":[0.2848029638],"iteration":634,"passed_time":5.787011197,"remaining_time":3.326392263},
{"learn":[0.2843045847],"iteration":635,"passed_time":5.795868043,"remaining_time":3.317132025},
{"learn":[0.2841884681],"iteration":636,"passed_time":5.803455103,"remaining_time":3.307149454},
{"learn":[0.2841853969],"iteration":637,"passed_time":5.810130896,"remaining_time":3.296657342},
{"learn":[0.2840998656],"iteration":638,"passed_time":5.817219166,"remaining_time":3.286410202},
{"learn":[0.2839723862],"iteration":639,"passed_time":5.8260623,"remaining_time":3.277160044},
{"learn":[0.2839346199],"iteration":640,"passed_time":5.833552031,"remaining_time":3.267153166},
{"learn":[0.2839331468],"iteration":641,"passed_time":5.841739529,"remaining_time":3.257543226},
{"learn":[0.283772446],"iteration":642,"passed_time":5.850930669,"remaining_time":3.248494944},
{"learn":[0.2837340909],"iteration":643,"passed_time":5.857837855,"remaining_time":3.238183659},
{"learn":[0.2836547138],"iteration":644,"passed_time":5.866625359,"remaining_time":3.228917833},
{"learn":[0.283479663],"iteration":645,"passed_time":5.87494232,"remaining_time":3.219395637},
{"learn":[0.283461599],"iteration":646,"passed_time":5.884002543,"remaining_time":3.210282686},
{"learn":[0.2833211534],"iteration":647,"passed_time":5.89063331,"remaining_time":3.199850193},
{"learn":[0.2832609858],"iteration":648,"passed_time":5.898900635,"remaining_time":3.190314519},
{"learn":[0.2832074068],"iteration":649,"passed_time":5.906815352,"remaining_time":3.180592882},
{"learn":[0.2829257264],"iteration":650,"passed_time":5.914373735,"remaining_time":3.170685766},
{"learn":[0.282787404],"iteration":651,"passed_time":5.921285741,"remaining_time":3.160440856},
{"learn":[0.2827750377],"iteration":652,"passed_time":5.92977255,"remaining_time":3.151042994},
{"learn":[0.2825342232],"iteration":653,"passed_time":5.936736298,"remaining_time":3.140842139},
{"learn":[0.2823498686],"iteration":654,"passed_time":5.94420865,"remaining_time":3.13091906},
{"learn":[0.282034043],"iteration":655,"passed_time":5.954055848,"remaining_time":3.122248798},
{"learn":[0.281706071],"iteration":656,"passed_time":5.961717211,"remaining_time":3.112433795},
{"learn":[0.281690139],"iteration":657,"passed_time":5.968562331,"remaining_time":3.10220109},
{"learn":[0.2816885033],"iteration":658,"passed_time":5.976385193,"remaining_time":3.092484599},
{"learn":[0.2816671299],"iteration":659,"passed_time":5.984397009,"remaining_time":3.082871186},
{"learn":[0.2816553514],"iteration":660,"passed_time":5.992053842,"remaining_time":3.073080563},
{"learn":[0.2815861689],"iteration":661,"passed_time":6.000329957,"remaining_time":3.063612576},
{"learn":[0.2814073625],"iteration":662,"passed_time":6.009759817,"remaining_time":3.054734628},
{"learn":[0.281364647],"iteration":663,"passed_time":6.019053808,"remaining_time":3.045786264},
{"learn":[0.2812268605],"iteration":664,"passed_time":6.03120918,"remaining_time":3.038278309},
{"learn":[0.2812199908],"iteration":665,"passed_time":6.040550352,"remaining_time":3.029345071},
{"learn":[0.2811294923],"iteration":666,"passed_time":6.04953557,"remaining_time":3.020232901},
{"learn":[0.2805034102],"iteration":667,"passed_time":6.058831164,"remaining_time":3.011275369},
{"learn":[0.2805022416],"iteration":668,"passed_time":6.066836806,"remaining_time":3.001678599},
{"learn":[0.2804756323],"iteration":669,"passed_time":6.073608714,"remaining_time":2.991478919},
{"learn":[0.2802829774],"iteration":670,"passed_time":6.080468709,"remaining_time":2.981332646},
{"learn":[0.2802823623],"iteration":671,"passed_time":6.090434876,"remaining_time":2.972712261},
{"learn":[0.2802448401],"iteration":672,"passed_time":6.099202644,"remaining_time":2.963505594},
{"learn":[0.2802263292],"iteration":673,"passed_time":6.106125827,"remaining_time":2.953408041},
{"learn":[0.2801927692],"iteration":674,"passed_time":6.112898206,"remaining_time":2.943247284},
{"learn":[0.2801262122],"iteration":675,"passed_time":6.129339396,"remaining_time":2.937730716},
{"learn":[0.280078334],"iteration":676,"passed_time":6.139422698,"remaining_time":2.929148495},
{"learn":[0.2800243415],"iteration":677,"passed_time":6.149016774,"remaining_time":2.9203295},
{"learn":[0.2800074135],"iteration":678,"passed_time":6.156993397,"remaining_time":2.910743565},
{"learn":[0.2799736487],"iteration":679,"passed_time":6.164802697,"remaining_time":2.901083622},
{"learn":[0.279891695],"iteration":680,"passed_time":6.17207155,"remaining_time":2.891175954},
{"learn":[0.2798345568],"iteration":681,"passed_time":6.179581529,"remaining_time":2.881388455},
{"learn":[0.2795786779],"iteration":682,"passed_time":6.188068999,"remaining_time":2.872061307},
{"learn":[0.2795594486],"iteration":683,"passed_time":6.195802803,"remaining_time":2.862388429},
{"learn":[0.2795568179],"iteration":684,"passed_time":6.204590567,"remaining_time":2.853205881},
{"learn":[0.2795481604],"iteration":685,"passed_time":6.213497792,"remaining_time":2.844079164},
{"learn":[0.279488587],"iteration":686,"passed_time":6.223276179,"remaining_time":2.835349991},
{"learn":[0.2794874535],"iteration":687,"passed_time":6.231010545,"remaining_time":2.825690828},
{"learn":[0.2794646018],"iteration":688,"passed_time":6.239037686,"remaining_time":2.816169405},
{"learn":[0.2794456628],"iteration":689,"passed_time":6.248632182,"remaining_time":2.807356488},
{"learn":[0.2793989187],"iteration":690,"passed_time":6.28771506,"remaining_time":2.811727863},
{"learn":[0.2791300086],"iteration":691,"passed_time":6.295456311,"remaining_time":2.802023907},
{"learn":[0.2788744813],"iteration":692,"passed_time":6.303524288,"remaining_time":2.792470356},
{"learn":[0.2788644401],"iteration":693,"passed_time":6.311728013,"remaining_time":2.78298094},
{"learn":[0.2788534036],"iteration":694,"passed_time":6.320961724,"remaining_time":2.773947231},
{"learn":[0.2787844071],"iteration":695,"passed_time":6.329194567,"remaining_time":2.764475788},
{"learn":[0.278718337],"iteration":696,"passed_time":6.338648644,"remaining_time":2.755538794},
{"learn":[0.2785690292],"iteration":697,"passed_time":6.345908687,"remaining_time":2.745651037},
{"learn":[0.2785077976],"iteration":698,"passed_time":6.353954692,"remaining_time":2.736109245},
{"learn":[0.278230784],"iteration":699,"passed_time":6.360135485,"remaining_time":2.725772351},
{"learn":[0.2782236437],"iteration":700,"passed_time":6.36913653,"remaining_time":2.716650246},
{"learn":[0.2782038387],"iteration":701,"passed_time":6.376358474,"remaining_time":2.706773255},
{"learn":[0.2778243117],"iteration":702,"passed_time":6.384005402,"remaining_time":2.697083363},
{"learn":[0.2778064504],"iteration":703,"passed_time":6.393072753,"remaining_time":2.687996498},
{"learn":[0.2774459738],"iteration":704,"passed_time":6.401273,"remaining_time":2.678546858},
{"learn":[0.2774446523],"iteration":705,"passed_time":6.40805862,"remaining_time":2.668511663},
{"learn":[0.2773282732],"iteration":706,"passed_time":6.416180384,"remaining_time":2.659039395},
{"learn":[0.277278212],"iteration":707,"passed_time":6.423226876,"remaining_time":2.649127468},
{"learn":[0.2772411444],"iteration":708,"passed_time":6.43120849,"remaining_time":2.639607434},
{"learn":[0.2772350483],"iteration":709,"passed_time":6.438718449,"remaining_time":2.629899085},
{"learn":[0.2772236487],"iteration":710,"passed_time":6.446235955,"remaining_time":2.620199987},
{"learn":[0.2771594509],"iteration":711,"passed_time":6.456350973,"remaining_time":2.611557697},
{"learn":[0.2771594421],"iteration":712,"passed_time":6.465363474,"remaining_time":2.602467485},
{"learn":[0.2771277556],"iteration":713,"passed_time":6.471916338,"remaining_time":2.592392259},
{"learn":[0.2771221931],"iteration":714,"passed_time":6.478683736,"remaining_time":2.582412398},
{"learn":[0.2770990248],"iteration":715,"passed_time":6.485357313,"remaining_time":2.572404297},
{"learn":[0.2770813011],"iteration":716,"passed_time":6.49186012,"remaining_time":2.562338095},
{"learn":[0.2770763239],"iteration":717,"passed_time":6.49935343,"remaining_time":2.552670846},
{"learn":[0.2770446692],"iteration":718,"passed_time":6.506252085,"remaining_time":2.542777241},
{"learn":[0.2769492384],"iteration":719,"passed_time":6.5136877,"remaining_time":2.533100772},
{"learn":[0.2768115278],"iteration":720,"passed_time":6.522208458,"remaining_time":2.52385043},
{"learn":[0.2766638695],"iteration":721,"passed_time":6.529138457,"remaining_time":2.5139896},
{"learn":[0.2766428931],"iteration":722,"passed_time":6.538161253,"remaining_time":2.504938682},
{"learn":[0.2766032532],"iteration":723,"passed_time":6.546231505,"remaining_time":2.495524718},
{"learn":[0.276230379],"iteration":724,"passed_time":6.553628259,"remaining_time":2.485858995},
{"learn":[0.2762199457],"iteration":725,"passed_time":6.561230794,"remaining_time":2.476277187},
{"learn":[0.2762068405],"iteration":726,"passed_time":6.568162798,"remaining_time":2.466449029},
{"learn":[0.2760793904],"iteration":727,"passed_time":6.574755947,"remaining_time":2.456502222},
{"learn":[0.2760251392],"iteration":728,"passed_time":6.581652848,"remaining_time":2.446677533},
{"learn":[0.2757467142],"iteration":729,"passed_time":6.590121043,"remaining_time":2.43744203},
{"learn":[0.2756854769],"iteration":730,"passed_time":6.59763868,"remaining_time":2.42785883},
{"learn":[0.2755033937],"iteration":731,"passed_time":6.607054798,"remaining_time":2.418976347},
{"learn":[0.275386394],"iteration":732,"passed_time":6.616207558,"remaining_time":2.409996478},
{"learn":[0.2753729372],"iteration":733,"passed_time":6.624155174,"remaining_time":2.400579395},
{"learn":[0.2753541187],"iteration":734,"passed_time":6.633129847,"remaining_time":2.391536612},
{"learn":[0.2753515779],"iteration":735,"passed_time":6.64235215,"remaining_time":2.382582836},
{"learn":[0.2753428141],"iteration":736,"passed_time":6.651826054,"remaining_time":2.373718117},
{"learn":[0.2751665159],"iteration":737,"passed_time":6.65944162,"remaining_time":2.364192011},
{"learn":[0.2750510385],"iteration":738,"passed_time":6.670101083,"remaining_time":2.35574612},
{"learn":[0.2750487476],"iteration":739,"passed_time":6.681390653,"remaining_time":2.347515635},
{"learn":[0.2749757634],"iteration":740,"passed_time":6.690922774,"remaining_time":2.338662616},
{"learn":[0.2747204453],"iteration":741,"passed_time":6.699804799,"remaining_time":2.329581723},
{"learn":[0.2746102164],"iteration":742,"passed_time":6.706800081,"remaining_time":2.319848749},
{"learn":[0.2744410649],"iteration":743,"passed_time":6.714214175,"remaining_time":2.310267243},
{"learn":[0.2744110131],"iteration":744,"passed_time":6.720986144,"remaining_time":2.300471767},
{"learn":[0.2742475185],"iteration":745,"passed_time":6.731782628,"remaining_time":2.292054675},
{"learn":[0.2742267583],"iteration":746,"passed_time":6.739478472,"remaining_time":2.282581062},
{"learn":[0.2742116644],"iteration":747,"passed_time":6.746516886,"remaining_time":2.272890716},
{"learn":[0.2741993486],"iteration":748,"passed_time":6.75548729,"remaining_time":2.263854886},
{"learn":[0.2741867148],"iteration":749,"passed_time":6.765285933,"remaining_time":2.255095311},
{"learn":[0.2741386102],"iteration":750,"passed_time":6.774498414,"remaining_time":2.246138622},
{"learn":[0.2741078867],"iteration":751,"passed_time":6.782928801,"remaining_time":2.236923328},
{"learn":[0.274038797],"iteration":752,"passed_time":6.791221676,"remaining_time":2.227665012},
{"learn":[0.2738254],"iteration":753,"passed_time":6.822078395,"remaining_time":2.225770935},
{"learn":[0.2738041292],"iteration":754,"passed_time":6.829052658,"remaining_time":2.2160502},
{"learn":[0.2737092174],"iteration":755,"passed_time":6.836846663,"remaining_time":2.206601304},
{"learn":[0.2736979163],"iteration":756,"passed_time":6.847161227,"remaining_time":2.197965889},
{"learn":[0.2736177985],"iteration":757,"passed_time":6.855674208,"remaining_time":2.188750868},
{"learn":[0.2732036281],"iteration":758,"passed_time":6.862783236,"remaining_time":2.17909191},
{"learn":[0.2729301091],"iteration":759,"passed_time":6.87048702,"remaining_time":2.16962748},
{"learn":[0.2728892092],"iteration":760,"passed_time":6.880042785,"remaining_time":2.160749311},
{"learn":[0.2728874616],"iteration":761,"passed_time":6.888920781,"remaining_time":2.151657672},
{"learn":[0.2727317616],"iteration":762,"passed_time":6.897106023,"remaining_time":2.142351412},
{"learn":[0.2726785197],"iteration":763,"passed_time":6.904415221,"remaining_time":2.132777477},
{"learn":[0.2726458178],"iteration":764,"passed_time":6.912492891,"remaining_time":2.123445529},
{"learn":[0.2726384029],"iteration":765,"passed_time":6.919992566,"remaining_time":2.113940288},
{"learn":[0.2725732566],"iteration":766,"passed_time":6.9270829,"remaining_time":2.104315927},
{"learn":[0.272239226],"iteration":767,"passed_time":6.934063518,"remaining_time":2.094665021},
{"learn":[0.2721533389],"iteration":768,"passed_time":6.940924384,"remaining_time":2.084985088},
{"learn":[0.2721222469],"iteration":769,"passed_time":6.948370192,"remaining_time":2.0754872},
{"learn":[0.2718800857],"iteration":770,"passed_time":6.958693778,"remaining_time":2.066849384},
{"learn":[0.2718718644],"iteration":771,"passed_time":6.965872521,"remaining_time":2.057278413},
{"learn":[0.2718232317],"iteration":772,"passed_time":6.972383727,"remaining_time":2.047517602},
{"learn":[0.2717922184],"iteration":773,"passed_time":6.980754124,"remaining_time":2.038308052},
{"learn":[0.2716682502],"iteration":774,"passed_time":7.010238546,"remaining_time":2.035230546},
{"learn":[0.2714498429],"iteration":775,"passed_time":7.018057569,"remaining_time":2.025831051},
{"learn":[0.2714433046],"iteration":776,"passed_time":7.025475262,"remaining_time":2.016320442},
{"learn":[0.2713602421],"iteration":777,"passed_time":7.033137817,"remaining_time":2.006885084},
{"learn":[0.2713585292],"iteration":778,"passed_time":7.042807551,"remaining_time":1.998023708},
{"learn":[0.2712674302],"iteration":779,"passed_time":7.05091471,"remaining_time":1.988719533},
{"learn":[0.2711986532],"iteration":780,"passed_time":7.059616282,"remaining_time":1.979585103},
{"learn":[0.2711830705],"iteration":781,"passed_time":7.067467851,"remaining_time":1.970214823},
{"learn":[0.2711816625],"iteration":782,"passed_time":7.087032795,"remaining_time":1.964094657},
{"learn":[0.2711755151],"iteration":783,"passed_time":7.094840131,"remaining_time":1.954700852},
{"learn":[0.271042638],"iteration":784,"passed_time":7.102412447,"remaining_time":1.945246721},
{"learn":[0.2710275232],"iteration":785,"passed_time":7.111148971,"remaining_time":1.936114351},
{"learn":[0.2708715791],"iteration":786,"passed_time":7.120272884,"remaining_time":1.927087833},
{"learn":[0.2708630739],"iteration":787,"passed_time":7.128920299,"remaining_time":1.917932872},
{"learn":[0.2707778247],"iteration":788,"passed_time":7.139209094,"remaining_time":1.909218148},
{"learn":[0.2706620101],"iteration":789,"passed_time":7.146753714,"remaining_time":1.899769975},
{"learn":[0.2706460798],"iteration":790,"passed_time":7.153154632,"remaining_time":1.890024422},
{"learn":[0.2705591756],"iteration":791,"passed_time":7.159855845,"remaining_time":1.880366181},
{"learn":[0.2704531631],"iteration":792,"passed_time":7.166856238,"remaining_time":1.870793495},
{"learn":[0.270444972],"iteration":793,"passed_time":7.173938174,"remaining_time":1.861248443},
{"learn":[0.2703813602],"iteration":794,"passed_time":7.182389329,"remaining_time":1.852062657},
{"learn":[0.2701429094],"iteration":795,"passed_time":7.189110969,"remaining_time":1.842435475},
{"learn":[0.269884786],"iteration":796,"passed_time":7.196575491,"remaining_time":1.833004799},
{"learn":[0.2698394806],"iteration":797,"passed_time":7.205899143,"remaining_time":1.824049658},
{"learn":[0.2697596442],"iteration":798,"passed_time":7.21372005,"remaining_time":1.814715557},
{"learn":[0.2697329282],"iteration":799,"passed_time":7.221284657,"remaining_time":1.805321164},
{"learn":[0.2697088837],"iteration":800,"passed_time":7.22891583,"remaining_time":1.795947878},
{"learn":[0.2696999834],"iteration":801,"passed_time":7.235455885,"remaining_time":1.786309558},
{"learn":[0.2695202657],"iteration":802,"passed_time":7.243324453,"remaining_time":1.777004878},
{"learn":[0.269338244],"iteration":803,"passed_time":7.250382092,"remaining_time":1.767506082},
{"learn":[0.2693319586],"iteration":804,"passed_time":7.257903808,"remaining_time":1.758125767},
{"learn":[0.2692974474],"iteration":805,"passed_time":7.266417631,"remaining_time":1.748988859},
{"learn":[0.2691985175],"iteration":806,"passed_time":7.276749265,"remaining_time":1.740288238},
{"learn":[0.2691280145],"iteration":807,"passed_time":7.284212725,"remaining_time":1.730902034},
{"learn":[0.2691211575],"iteration":808,"passed_time":7.292578721,"remaining_time":1.721733666},
{"learn":[0.269069523],"iteration":809,"passed_time":7.300113607,"remaining_time":1.712372328},
{"learn":[0.2690630635],"iteration":810,"passed_time":7.307712806,"remaining_time":1.703030481},
{"learn":[0.2690606651],"iteration":811,"passed_time":7.314844187,"remaining_time":1.693584615},
{"learn":[0.2690559945],"iteration":812,"passed_time":7.322600413,"remaining_time":1.684288164},
{"learn":[0.269054978],"iteration":813,"passed_time":7.331637733,"remaining_time":1.675288229},
{"learn":[0.2690543411],"iteration":814,"passed_time":7.338612727,"remaining_time":1.665820067},
{"learn":[0.2690323301],"iteration":815,"passed_time":7.34760027,"remaining_time":1.656811826},
{"learn":[0.2689990809],"iteration":816,"passed_time":7.354546297,"remaining_time":1.647346355},
{"learn":[0.268876463],"iteration":817,"passed_time":7.36259145,"remaining_time":1.638131594},
{"learn":[0.2688287698],"iteration":818,"passed_time":7.36963256,"remaining_time":1.628697794},
{"learn":[0.2688229828],"iteration":819,"passed_time":7.378318304,"remaining_time":1.619630847},
{"learn":[0.2687904074],"iteration":820,"passed_time":7.386587124,"remaining_time":1.610473928},
{"learn":[0.2687414308],"iteration":821,"passed_time":7.394209335,"remaining_time":1.60117915},
{"learn":[0.2686053315],"iteration":822,"passed_time":7.401256829,"remaining_time":1.591764834},
{"learn":[0.2685971626],"iteration":823,"passed_time":7.408772531,"remaining_time":1.582456269},
{"learn":[0.2683436133],"iteration":824,"passed_time":7.415447552,"remaining_time":1.572973723},
{"learn":[0.2683238401],"iteration":825,"passed_time":7.422637721,"remaining_time":1.563606493},
{"learn":[0.2683111143],"iteration":826,"passed_time":7.429924296,"remaining_time":1.554264696},
{"learn":[0.2682686016],"iteration":827,"passed_time":7.436989752,"remaining_time":1.544881929},
{"learn":[0.268245486],"iteration":828,"passed_time":7.443631836,"remaining_time":1.535417423},
{"learn":[0.2682177431],"iteration":829,"passed_time":7.45050425,"remaining_time":1.526006895},
{"learn":[0.2682083607],"iteration":830,"passed_time":7.459475946,"remaining_time":1.517029404},
{"learn":[0.2680983727],"iteration":831,"passed_time":7.469186394,"remaining_time":1.508201099},
{"learn":[0.2680582891],"iteration":832,"passed_time":7.476186407,"remaining_time":1.498827287},
{"learn":[0.2680487364],"iteration":833,"passed_time":7.483533654,"remaining_time":1.489528281},
{"learn":[0.2680056187],"iteration":834,"passed_time":7.490766463,"remaining_time":1.480211337},
{"learn":[0.2679909944],"iteration":835,"passed_time":7.498286996,"remaining_time":1.470955822},
{"learn":[0.2679836784],"iteration":836,"passed_time":7.506478493,"remaining_time":1.461835119},
{"learn":[0.2674882428],"iteration":837,"passed_time":7.515459512,"remaining_time":1.452869261},
{"learn":[0.2674584648],"iteration":838,"passed_time":7.522227741,"remaining_time":1.443478744},
{"learn":[0.2673785865],"iteration":839,"passed_time":7.52913645,"remaining_time":1.434121229},
{"learn":[0.2673623561],"iteration":840,"passed_time":7.535762566,"remaining_time":1.424716109},
{"learn":[0.2673143134],"iteration":841,"passed_time":7.542283837,"remaining_time":1.415297917},
{"learn":[0.2672372063],"iteration":842,"passed_time":7.548794883,"remaining_time":1.405884694},
{"learn":[0.2671883204],"iteration":843,"passed_time":7.555489199,"remaining_time":1.396512222},
{"learn":[0.267171611],"iteration":844,"passed_time":7.562332715,"remaining_time":1.387173457},
{"learn":[0.2670335813],"iteration":845,"passed_time":7.568837347,"remaining_time":1.377778902},
{"learn":[0.2670245061],"iteration":846,"passed_time":7.576353018,"remaining_time":1.368573804},
{"learn":[0.2669007991],"iteration":847,"passed_time":7.582979586,"remaining_time":1.359213322},
{"learn":[0.2668521998],"iteration":848,"passed_time":7.59047478,"remaining_time":1.350013771},
{"learn":[0.2668055022],"iteration":849,"passed_time":7.598381039,"remaining_time":1.340890772},
{"learn":[0.266620551],"iteration":850,"passed_time":7.607138622,"remaining_time":1.331919688},
{"learn":[0.2665678608],"iteration":851,"passed_time":7.613742657,"remaining_time":1.322575015},
{"learn":[0.2664190766],"iteration":852,"passed_time":7.620736646,"remaining_time":1.313303971},
{"learn":[0.2664151715],"iteration":853,"passed_time":7.627834127,"remaining_time":1.304055951},
{"learn":[0.266148493],"iteration":854,"passed_time":7.636341154,"remaining_time":1.295052008},
{"learn":[0.266139462],"iteration":855,"passed_time":7.643055768,"remaining_time":1.285747699},
{"learn":[0.2661358434],"iteration":856,"passed_time":7.650526914,"remaining_time":1.27657567},
{"learn":[0.2660949717],"iteration":857,"passed_time":7.658012086,"remaining_time":1.267409926},
{"learn":[0.2660074223],"iteration":858,"passed_time":7.664717628,"remaining_time":1.258120123},
{"learn":[0.2659815953],"iteration":859,"passed_time":7.672451983,"remaining_time":1.249003811},
{"learn":[0.2659458503],"iteration":860,"passed_time":7.680153862,"remaining_time":1.239885467},
{"learn":[0.2658770805],"iteration":861,"passed_time":7.688005312,"remaining_time":1.230794354},
{"learn":[0.2658151307],"iteration":862,"passed_time":7.696932924,"remaining_time":1.221876953},
{"learn":[0.2657851688],"iteration":863,"passed_time":7.704929593,"remaining_time":1.212812992},
{"learn":[0.2657298906],"iteration":864,"passed_time":7.711662029,"remaining_time":1.203554189},
{"learn":[0.2655050088],"iteration":865,"passed_time":7.718394565,"remaining_time":1.194301238},
{"learn":[0.2654614692],"iteration":866,"passed_time":7.725192456,"remaining_time":1.185064125},
{"learn":[0.2654558504],"iteration":867,"passed_time":7.73326029,"remaining_time":1.176025758},
{"learn":[0.2654239456],"iteration":868,"passed_time":7.741177755,"remaining_time":1.166966957},
{"learn":[0.2654153701],"iteration":869,"passed_time":7.748888274,"remaining_time":1.157879857},
{"learn":[0.2653804119],"iteration":870,"passed_time":7.758245804,"remaining_time":1.149039849},
{"learn":[0.2653571985],"iteration":871,"passed_time":7.766813092,"remaining_time":1.140082656},
{"learn":[0.2653490144],"iteration":872,"passed_time":7.773946408,"remaining_time":1.130917748},
{"learn":[0.2650770018],"iteration":873,"passed_time":7.781899575,"remaining_time":1.121875682},
{"learn":[0.2649470058],"iteration":874,"passed_time":7.788935883,"remaining_time":1.112705126},
{"learn":[0.2647448808],"iteration":875,"passed_time":7.797034713,"remaining_time":1.103689845},
{"learn":[0.2646913374],"iteration":876,"passed_time":7.805431751,"remaining_time":1.094718478},
{"learn":[0.264672168],"iteration":877,"passed_time":7.813187526,"remaining_time":1.085659315},
{"learn":[0.264656941],"iteration":878,"passed_time":7.820171231,"remaining_time":1.076496836},
{"learn":[0.2644974631],"iteration":879,"passed_time":7.827347658,"remaining_time":1.06736559},
{"learn":[0.2642137991],"iteration":880,"passed_time":7.83538761,"remaining_time":1.058355421},
{"learn":[0.2641322283],"iteration":881,"passed_time":7.843871902,"remaining_time":1.049406898},
{"learn":[0.2641276652],"iteration":882,"passed_time":7.851672592,"remaining_time":1.040368849},
{"learn":[0.264056429],"iteration":883,"passed_time":7.861139279,"remaining_time":1.031552213},
{"learn":[0.26395819],"iteration":884,"passed_time":7.867794985,"remaining_time":1.02236884},
{"learn":[0.2638559405],"iteration":885,"passed_time":7.876808509,"remaining_time":1.013494549},
{"learn":[0.2638450883],"iteration":886,"passed_time":7.885802577,"remaining_time":1.004617465},
{"learn":[0.2638070362],"iteration":887,"passed_time":7.892850914,"remaining_time":0.9954947098},
{"learn":[0.2638015339],"iteration":888,"passed_time":7.899095275,"remaining_time":0.9862762379},
{"learn":[0.2638014875],"iteration":889,"passed_time":7.905644441,"remaining_time":0.9771021219},
{"learn":[0.2637588201],"iteration":890,"passed_time":7.913113784,"remaining_time":0.9680464674},
{"learn":[0.2636798658],"iteration":891,"passed_time":7.920739725,"remaining_time":0.9590133299},
{"learn":[0.2634469247],"iteration":892,"passed_time":7.928280998,"remaining_time":0.9499731991},
{"learn":[0.2634277102],"iteration":893,"passed_time":7.936747037,"remaining_time":0.9410460693},
{"learn":[0.2633194469],"iteration":894,"passed_time":7.944507723,"remaining_time":0.9320372189},
{"learn":[0.2633173267],"iteration":895,"passed_time":7.965450287,"remaining_time":0.924561194},
{"learn":[0.2631450696],"iteration":896,"passed_time":7.973060421,"remaining_time":0.9155242178},
{"learn":[0.2631394664],"iteration":897,"passed_time":7.980676348,"remaining_time":0.9064910774},
{"learn":[0.2629776148],"iteration":898,"passed_time":7.988633374,"remaining_time":0.8974994114},
{"learn":[0.2629114864],"iteration":899,"passed_time":7.998788646,"remaining_time":0.888754294},
{"learn":[0.2628620567],"iteration":900,"passed_time":8.007374618,"remaining_time":0.879833615},
{"learn":[0.2628564835],"iteration":901,"passed_time":8.01634486,"remaining_time":0.8709554283},
{"learn":[0.2628557737],"iteration":902,"passed_time":8.024908449,"remaining_time":0.862033355},
{"learn":[0.2626376898],"iteration":903,"passed_time":8.033186388,"remaining_time":0.8530817403},
{"learn":[0.2626136214],"iteration":904,"passed_time":8.042081013,"remaining_time":0.8441963495},
{"learn":[0.2625631079],"iteration":905,"passed_time":8.050099876,"remaining_time":0.8352200754},
{"learn":[0.2625283739],"iteration":906,"passed_time":8.058420586,"remaining_time":0.8262768627},
{"learn":[0.2625061598],"iteration":907,"passed_time":8.065819253,"remaining_time":0.8172415983},
{"learn":[0.2623701777],"iteration":908,"passed_time":8.074842781,"remaining_time":0.8083725996},
{"learn":[0.2622183982],"iteration":909,"passed_time":8.083662713,"remaining_time":0.7994831255},
{"learn":[0.2621557893],"iteration":910,"passed_time":8.091602908,"remaining_time":0.7905078582},
{"learn":[0.2621250363],"iteration":911,"passed_time":8.099939064,"remaining_time":0.7815730676},
{"learn":[0.2621219039],"iteration":912,"passed_time":8.110103116,"remaining_time":0.772813769},
{"learn":[0.2619321076],"iteration":913,"passed_time":8.118543927,"remaining_time":0.7638892535},
{"learn":[0.2619297258],"iteration":914,"passed_time":8.126552695,"remaining_time":0.7549256602},
{"learn":[0.2618987458],"iteration":915,"passed_time":8.135476057,"remaining_time":0.7460480227},
{"learn":[0.2618393792],"iteration":916,"passed_time":8.142677173,"remaining_time":0.7370144006},
{"learn":[0.2618066734],"iteration":917,"passed_time":8.150445026,"remaining_time":0.7280353945},
{"learn":[0.2618035397],"iteration":918,"passed_time":8.158231903,"remaining_time":0.7190607009},
{"learn":[0.2617737229],"iteration":919,"passed_time":8.166035301,"remaining_time":0.7100900261},
{"learn":[0.2617469539],"iteration":920,"passed_time":8.174411299,"remaining_time":0.7011710018},
{"learn":[0.261635957],"iteration":921,"passed_time":8.184073284,"remaining_time":0.6923619481},
{"learn":[0.2615620633],"iteration":922,"passed_time":8.191841769,"remaining_time":0.6833930837},
{"learn":[0.2614517556],"iteration":923,"passed_time":8.199213374,"remaining_time":0.6743941736},
{"learn":[0.2614452291],"iteration":924,"passed_time":8.207802081,"remaining_time":0.6654974661},
{"learn":[0.2613335332],"iteration":925,"passed_time":8.216219638,"remaining_time":0.6565877464},
{"learn":[0.2612790411],"iteration":926,"passed_time":8.22486989,"remaining_time":0.6476974131},
{"learn":[0.2612511043],"iteration":927,"passed_time":8.232112202,"remaining_time":0.6386983605},
{"learn":[0.2611557879],"iteration":928,"passed_time":8.240772447,"remaining_time":0.6298114572},
{"learn":[0.26115429],"iteration":929,"passed_time":8.250342297,"remaining_time":0.6209935062},
{"learn":[0.261150177],"iteration":930,"passed_time":8.260293699,"remaining_time":0.6122022183},
{"learn":[0.2611447669],"iteration":931,"passed_time":8.268302437,"remaining_time":0.6032667014},
{"learn":[0.2611351479],"iteration":932,"passed_time":8.275076721,"remaining_time":0.5942445234},
{"learn":[0.2611214741],"iteration":933,"passed_time":8.282588002,"remaining_time":0.5852792379},
{"learn":[0.2611088947],"iteration":934,"passed_time":8.289347451,"remaining_time":0.5762647961},
{"learn":[0.2610698874],"iteration":935,"passed_time":8.298056431,"remaining_time":0.5673884739},
{"learn":[0.2610412049],"iteration":936,"passed_time":8.307695632,"remaining_time":0.5585750532},
{"learn":[0.2610062295],"iteration":937,"passed_time":8.316357221,"remaining_time":0.5496952534},
{"learn":[0.2610011885],"iteration":938,"passed_time":8.325143202,"remaining_time":0.5408239993},
{"learn":[0.2608483627],"iteration":939,"passed_time":8.334865337,"remaining_time":0.5320126811},
{"learn":[0.2608230328],"iteration":940,"passed_time":8.343229148,"remaining_time":0.5231142611},
{"learn":[0.2608160607],"iteration":941,"passed_time":8.351361596,"remaining_time":0.5142027309},
{"learn":[0.2608120465],"iteration":942,"passed_time":8.358651399,"remaining_time":0.5052419191},
{"learn":[0.2606785331],"iteration":943,"passed_time":8.365290225,"remaining_time":0.4962460303},
{"learn":[0.2606703761],"iteration":944,"passed_time":8.372817284,"remaining_time":0.487306826},
{"learn":[0.2606132797],"iteration":945,"passed_time":8.381889776,"remaining_time":0.4784588244},
{"learn":[0.2605824493],"iteration":946,"passed_time":8.388921112,"remaining_time":0.4694961129},
{"learn":[0.2604179058],"iteration":947,"passed_time":8.395489894,"remaining_time":0.4605121039},
{"learn":[0.2602794982],"iteration":948,"passed_time":8.402482249,"remaining_time":0.4515559481},
{"learn":[0.2602261576],"iteration":949,"passed_time":8.409903921,"remaining_time":0.4426265222},
{"learn":[0.2602074329],"iteration":950,"passed_time":8.417391086,"remaining_time":0.4337036416},
{"learn":[0.2599964247],"iteration":951,"passed_time":8.425308911,"remaining_time":0.4248054913},
{"learn":[0.2599727992],"iteration":952,"passed_time":8.433700798,"remaining_time":0.4159327781},
{"learn":[0.2599604156],"iteration":953,"passed_time":8.442169003,"remaining_time":0.4070647528},
{"learn":[0.2598777233],"iteration":954,"passed_time":8.449622249,"remaining_time":0.3981497395},
{"learn":[0.2595198046],"iteration":955,"passed_time":8.457311317,"remaining_time":0.389248638},
{"learn":[0.2593695562],"iteration":956,"passed_time":8.464699099,"remaining_time":0.3803365321},
{"learn":[0.2591131406],"iteration":957,"passed_time":8.473247544,"remaining_time":0.3714784936},
{"learn":[0.2590915205],"iteration":958,"passed_time":8.479691242,"remaining_time":0.3625311167},
{"learn":[0.2590848965],"iteration":959,"passed_time":8.487670501,"remaining_time":0.3536529375},
{"learn":[0.2590626164],"iteration":960,"passed_time":8.495432791,"remaining_time":0.344767824},
{"learn":[0.2589376429],"iteration":961,"passed_time":8.503880108,"remaining_time":0.335912104},
{"learn":[0.2587774232],"iteration":962,"passed_time":8.512879529,"remaining_time":0.327078445},
{"learn":[0.2587674259],"iteration":963,"passed_time":8.520094937,"remaining_time":0.3181778192},
{"learn":[0.2587617064],"iteration":964,"passed_time":8.52660485,"remaining_time":0.3092550982},
{"learn":[0.2586006739],"iteration":965,"passed_time":8.534749126,"remaining_time":0.3003948968},
{"learn":[0.2584920558],"iteration":966,"passed_time":8.54330221,"remaining_time":0.2915501271},
{"learn":[0.2584773694],"iteration":967,"passed_time":8.550744861,"remaining_time":0.2826692516},
{"learn":[0.2583285066],"iteration":968,"passed_time":8.560712021,"remaining_time":0.273872108},
{"learn":[0.2583158072],"iteration":969,"passed_time":8.569413544,"remaining_time":0.2650334086},
{"learn":[0.2582608577],"iteration":970,"passed_time":8.577648744,"remaining_time":0.2561810645},
{"learn":[0.258239967],"iteration":971,"passed_time":8.585975196,"remaining_time":0.2473326188},
{"learn":[0.2581968342],"iteration":972,"passed_time":8.594921154,"remaining_time":0.238502437},
{"learn":[0.2581784732],"iteration":973,"passed_time":8.603375074,"remaining_time":0.2296588829},
{"learn":[0.2581663639],"iteration":974,"passed_time":8.611824666,"remaining_time":0.2208160171},
{"learn":[0.2577405707],"iteration":975,"passed_time":8.620791179,"remaining_time":0.2119866683},
{"learn":[0.257661058],"iteration":976,"passed_time":8.62798649,"remaining_time":0.2031153421},
{"learn":[0.2575981241],"iteration":977,"passed_time":8.634391438,"remaining_time":0.1942296642},
{"learn":[0.2574992686],"iteration":978,"passed_time":8.643926906,"remaining_time":0.1854162053},
{"learn":[0.2573298618],"iteration":979,"passed_time":8.65050539,"remaining_time":0.1765409263},
{"learn":[0.2572981926],"iteration":980,"passed_time":8.658191682,"remaining_time":0.1676917859},
{"learn":[0.2572543633],"iteration":981,"passed_time":8.666452261,"remaining_time":0.1588555404},
{"learn":[0.2572156081],"iteration":982,"passed_time":8.674272277,"remaining_time":0.1500128471},
{"learn":[0.2571874242],"iteration":983,"passed_time":8.682357245,"remaining_time":0.1411765406},
{"learn":[0.2570816308],"iteration":984,"passed_time":8.690828407,"remaining_time":0.1323476407},
{"learn":[0.2570380979],"iteration":985,"passed_time":8.699002753,"remaining_time":0.1235152521},
{"learn":[0.2570326407],"iteration":986,"passed_time":8.70690424,"remaining_time":0.114680603},
{"learn":[0.2570163478],"iteration":987,"passed_time":8.714478259,"remaining_time":0.1058438655},
{"learn":[0.2569689594],"iteration":988,"passed_time":8.722444979,"remaining_time":0.09701404931},
{"learn":[0.2568817205],"iteration":989,"passed_time":8.730344822,"remaining_time":0.08818530123},
{"learn":[0.2568769563],"iteration":990,"passed_time":8.737361173,"remaining_time":0.0793504042},
{"learn":[0.256872953],"iteration":991,"passed_time":8.743922006,"remaining_time":0.07051550005},
{"learn":[0.2567884775],"iteration":992,"passed_time":8.751946121,"remaining_time":0.06169549128},
{"learn":[0.2567668351],"iteration":993,"passed_time":8.758961099,"remaining_time":0.05287099255},
{"learn":[0.2566221261],"iteration":994,"passed_time":8.767719856,"remaining_time":0.04405889375},
{"learn":[0.2564895971],"iteration":995,"passed_time":8.774892294,"remaining_time":0.0352405313},
{"learn":[0.2563998911],"iteration":996,"passed_time":8.783052829,"remaining_time":0.02642844382},
{"learn":[0.2563940347],"iteration":997,"passed_time":8.791784462,"remaining_time":0.01761880654},
{"learn":[0.256295732],"iteration":998,"passed_time":8.800516796,"remaining_time":0.008809326122},
{"learn":[0.2562101269],"iteration":999,"passed_time":8.809780537,"remaining_time":0}
]}